Workbook
Name SegmentaciónDeDatos_Categoría: #N/A
Name SegmentaciónDeDatos_Semana: #N/A

Sheet Dashboard
A1: TABLERO DE GASTOS — FV (Nov 2025 a May 2026)
A3: Total Pagado | B3: Total Pendiente | C3: Movimientos | D3: Semanas | E3: Prom. pagado/semana | F3: Ingresos totales | G3: Egresos totales
A4: =SUM(TablaGastos[Pago]) -> 7051503.6 | B4: =SUM(TablaGastos[Pendiente]) -> 5246593.9 | C4: =COUNTA(TablaGastos[Concepto]) -> 472 | D4: {=SUMPRODUCT(1/COUNTIF(TablaGastos[Semana],TablaGastos[Semana]))} -> 29 | E4: =A4/D4 -> 243155.3 | F4: =Pivots!V31 -> 8487715.8 | G4: =Pivots!W31 -> 306450
V5: ◄ Filtros interactivos
A66: RESUMEN MENSUAL
A67: Mes | B67: Ingresos | C67: Egresos | D67: Pagado | E67: Pendiente | F67: Balance
A68: {=Pivots!AA2:AF8} -> 1-Nov | B68: 736500.8 | C68: 12950 | D68: 743476 | E68: 329762 | F68: -19925.2
A69: 2-Dic | B69: 1758496.8 | C69: 42850 | D69: 1811975 | E69: 742446.26 | F69: -96328.22
A70: 3-Ene | B70: 1008213.1 | C70: 0 | D70: 605682.21 | E70: 783233.22 | F70: 402530.87
A71: 4-Feb | B71: 1214504 | C71: 0 | D71: 844914.57 | E71: 927193.04 | F71: 369589.43
A72: 5-Mar | B72: 1322706 | C72: 75850 | D72: 809867.03 | E72: 900505.74 | F72: 436988.97
A73: 6-Abr | B73: 1382415.3 | C73: 92750 | D73: 1198456.7 | E73: 543865.2 | F73: 91208.6
A74: 7-May | B74: 1064879.8 | C74: 82050 | D74: 1037132.1 | E74: 1019588.4 | F74: -54302.284
A85: MÉTRICAS MENSUALES — Pagado vs Pendiente y Gasto por categoría

Sheet Hoja1
B3: ARA | C3: 41000
B4: IMSS | C4: 44205.22 | D4: =SUM(C3:C4) -> 85205.22
B5: RAISA | C5: 48374.59 | G5: NOMINA 1 | H5: 45000 | K5: 20000 | M5: 76000
B6: NOMINA 1 | C6: 40000 | G6: FRESERO ALEX | H6: 90000 | I6: 205495.79 | M6: 16000
B7: NOMINA 2 | C7: 10000 | G7: TARIMA | H7: 16240 | M7: =SUM(M5:M6) -> 92000
B8: FRESERO ALEX | C8: 205495.79 | G8: CIPSA | H8: 2784
B9: FRESERO JOSE LUIS RODILES | C9: 230111.28
B10: FRESERO GABRIEL | C10: =2427*27 -> 65529 | G10: TROQUELADO Y ALUM DE ZAMORA | H10: 35323
B11: TARIMA | C11: 16240 | G11: IMSS CXM | H11: 49074.84
B12: CIPSA | C12: 2784 | G12: GARNICA CONSULTING (Factura 415) | H12: 4060
B13: BOLSA | C13: =1100*7 -> 7700 | G13: GARNICA CONSULTING (Factura 436) | H13: 4263
B14: ETIQUETA BLANCA | C14: 2532.45 | D14: Codice | G14: RICA GONZALEZ | H14: 15000
B15: CXM | C15: 33000 | G15: AVV | H15: 25000
B16: Suma | C16: =SUM(C2:C15) -> 746972.33 | G16: REPARACION CAMIONETA | H16: 3500
G17: AA | H17: 1800
B18: Deposito | C18: 719568 | G18: Nomina CXM | H18: 52000 | K18: =H18 -> 52000
G19: Grua | H19: 3600 | K19: 3600
B20: Saldo | C20: =C18-C16 -> -27404.332 | G20: Gasto regreso | H20: 2500
H21: =SUM(H5:H20) -> 350144.84 | K21: =SUM(K5:K20) -> 75600 | L21: =SUM(K17:K20) -> 55600
K22: =K21-M7 -> -16400
G23: CXM | H23: 166174.69 | I23: 76000
G24: FV | H24: 175000 | I24: 175000
H25: =SUM(H23:H24) -> 341174.69
H27: =H25-H21 -> -8970.15

Sheet Pivots
A1: Periodo | B1: Suma de Pago | C1: Suma de Pendiente | F1: Categoría | G1: Suma de Pago | J1: Concepto | K1: Suma de Pago | N1: Top Concepto | O1: Pago | R1: Categoría | S1: Pago | U1: Semana | V1: Ingresos | W1: Egresos | X1: Pagado | Y1: Mes | AA1: Mes | AB1: Ingresos | AC1: Egresos | AD1: Pagado | AE1: Pendiente | AF1: Balance | AH1: Mes | AI1: Pagado | AJ1: Pendiente | AL1: Suma de Pago | AM1: Categoría
A2: 01 10-15 NOV | B2: 311006 | C2: 18740 | F2: Empaque/Material | G2: 742050.47 | J2: Aceros Gutz | K2: 1076 | N2: {=_xlfn.TAKE(_xlfn.SORTBY(_xlfn.UNIQUE(TablaGastos[Concepto]),SUMIF(TablaGastos[Concepto],_xlfn.UNIQUE(TablaGastos[Concepto]),TablaGastos[Pago]),-1),12)} -> NOMINA FV | O2: {=SUMIF(TablaGastos[Concepto],_xlfn.ANCHORARRAY(N2),TablaGastos[Pago])} -> 3043298 | R2: {=_xlfn.SORTBY(_xlfn.UNIQUE(TablaGastos[Categoría]),SUMIF(TablaGastos[Categoría],_xlfn.UNIQUE(TablaGastos[Categoría]),TablaGastos[Pago]),-1)} -> Nómina/Personal | S2: {=SUMIF(TablaGastos[Categoría],_xlfn.ANCHORARRAY(R2),TablaGastos[Pago])} -> 4909233.7 | U2: 10-15 NOV | V2: ='10-15 NOV'!G11 -> 303500.8 | W2: 0 | X2: =SUMIFS(TablaGastos[Pago],TablaGastos[Semana],U2) -> 311006 | Y2: 1-Nov | AA2: 1-Nov | AB2: =SUMIF($Y$2:$Y$30,$AA2,$V$2:$V$30) -> 736500.8 | AC2: =SUMIF($Y$2:$Y$30,$AA2,$W$2:$W$30) -> 12950 | AD2: =SUMIF($Y$2:$Y$30,$AA2,$X$2:$X$30) -> 743476 | AE2: =SUMIFS(TablaGastos[Pendiente],TablaGastos[Mes],$AA2) -> 329762 | AF2: =AB2-AC2-AD2 -> -19925.2 | AH2: =AA2 -> 1-Nov | AI2: =AD2 -> 743476 | AJ2: =AE2 -> 329762 | AL2: Mes | AM2: Empaque/Material | AN2: Impuestos | AO2: LAR/Otros | AP2: Nómina/Personal | AQ2: Otros | AR2: Producto/Fruta | AS2: Servicios | AT2: Total general
A3: 02 17-22 NOV | B3: 292000 | C3: 186222 | F3: Impuestos | G3: 186766.93 | J3: ADEUDO GALU | K3: 0 | N3: NOMINA CXM | O3: 555402.5 | R3: Otros | S3: 837866.08 | U3: 17-22 NOV | V3: ='17-22 NOV'!G11 -> 295000 | W3: 0 | X3: =SUMIFS(TablaGastos[Pago],TablaGastos[Semana],U3) -> 292000 | Y3: 1-Nov | AA3: 2-Dic | AB3: =SUMIF($Y$2:$Y$30,$AA3,$V$2:$V$30) -> 1758496.8 | AC3: =SUMIF($Y$2:$Y$30,$AA3,$W$2:$W$30) -> 42850 | AD3: =SUMIF($Y$2:$Y$30,$AA3,$X$2:$X$30) -> 1811975 | AE3: =SUMIFS(TablaGastos[Pendiente],TablaGastos[Mes],$AA3) -> 742446.26 | AF3: =AB3-AC3-AD3 -> -96328.22 | AH3: =AA3 -> 2-Dic | AI3: =AD3 -> 1811975 | AJ3: =AE3 -> 742446.26 | AL3: 1-Nov | AM3: 15000 | AN3: 17470 | AP3: 650006 | AQ3: 0 | AR3: 37000 | AS3: 24000 | AT3: 743476
A4: 03 24-29 NOV | B4: 140470 | C4: 124800 | F4: LAR/Otros | G4: 2729 | J4: Alejandro Rodriguez | K4: 60000 | N4: RAISA | O4: 329928.42 | R4: Empaque/Material | S4: 742050.47 | U4: 24-29 NOV | V4: ='24-29 NOV'!G11 -> 138000 | W4: ='24-29 NOV'!J18 -> 12950 | X4: =SUMIFS(TablaGastos[Pago],TablaGastos[Semana],U4) -> 140470 | Y4: 1-Nov | AA4: 3-Ene | AB4: =SUMIF($Y$2:$Y$30,$AA4,$V$2:$V$30) -> 1008213.1 | AC4: =SUMIF($Y$2:$Y$30,$AA4,$W$2:$W$30) -> 0 | AD4: =SUMIF($Y$2:$Y$30,$AA4,$X$2:$X$30) -> 605682.21 | AE4: =SUMIFS(TablaGastos[Pendiente],TablaGastos[Mes],$AA4) -> 783233.22 | AF4: =AB4-AC4-AD4 -> 402530.87 | AH4: =AA4 -> 3-Ene | AI4: =AD4 -> 605682.21 | AJ4: =AE4 -> 783233.22 | AL4: 2-Dic | AM4: 95580.39 | AN4: 10000 | AP4: 972504.75 | AQ4: 638935.4 | AR4: 50000 | AS4: 44954.48 | AT4: 1811975
A5: 04 01-06 Dic | B5: 207784 | C5: 74150 | F5: Nómina/Personal | G5: 4909233.7 | J5: ALEX Y RAFA | K5: 184999.8 | N5: AVV (PAGO SANTANDER) | O5: 280000 | R5: Servicios | S5: 267089.42 | U5: 01-06 Dic | V5: ='01-06 Dic'!H11 -> 138000 | W5: ='01-06 Dic'!K18 -> 12950 | X5: =SUMIFS(TablaGastos[Pago],TablaGastos[Semana],U5) -> 207784 | Y5: 2-Dic | AA5: 4-Feb | AB5: =SUMIF($Y$2:$Y$30,$AA5,$V$2:$V$30) -> 1214504 | AC5: =SUMIF($Y$2:$Y$30,$AA5,$W$2:$W$30) -> 0 | AD5: =SUMIF($Y$2:$Y$30,$AA5,$X$2:$X$30) -> 844914.57 | AE5: =SUMIFS(TablaGastos[Pendiente],TablaGastos[Mes],$AA5) -> 927193.04 | AF5: =AB5-AC5-AD5 -> 369589.43 | AH5: =AA5 -> 4-Feb | AI5: =AD5 -> 844914.57 | AJ5: =AE5 -> 927193.04 | AL5: 3-Ene | AM5: 34481.54 | AN5: 30000 | AO5: 0 | AP5: 519300 | AQ5: 2041.71 | AS5: 19858.96 | AT5: 605682.21
A6: 05 08-13 Dic | B6: 446604 | C6: 294012.05 | F6: Otros | G6: 837866.08 | J6: ARTURO GUERRERO | K6: 240000 | N6: AVV (PAGO MONARCA) | O6: 260435 | R6: Impuestos | S6: 186766.93 | U6: 08-13 Dic | V6: ='08-13 Dic'!H11 -> 446470 | W6: ='08-13 Dic'!H20 -> 16950 | X6: =SUMIFS(TablaGastos[Pago],TablaGastos[Semana],U6) -> 446604 | Y6: 2-Dic | AA6: 5-Mar | AB6: =SUMIF($Y$2:$Y$30,$AA6,$V$2:$V$30) -> 1322706 | AC6: =SUMIF($Y$2:$Y$30,$AA6,$W$2:$W$30) -> 75850 | AD6: =SUMIF($Y$2:$Y$30,$AA6,$X$2:$X$30) -> 809867.03 | AE6: =SUMIFS(TablaGastos[Pendiente],TablaGastos[Mes],$AA6) -> 900505.74 | AF6: =AB6-AC6-AD6 -> 436988.97 | AH6: =AA6 -> 5-Mar | AI6: =AD6 -> 809867.03 | AJ6: =AE6 -> 900505.74 | AL6: 4-Feb | AM6: 124017.68 | AN6: 0 | AO6: 0 | AP6: 667778.29 | AQ6: 36900 | AS6: 16218.6 | AT6: 844914.57
A7: 06 15-20 Dic | B7: 392382.67 | C7: 159012.05 | F7: Producto/Fruta | G7: 105768 | J7: AVV | K7: 6500 | N7: ARTURO GUERRERO | O7: 240000 | R7: Producto/Fruta | S7: 105768 | U7: 15-20 Dic | V7: ='15-20 Dic'!H11 -> 381000 | W7: ='15-20 Dic'!H20 -> 12950 | X7: =SUMIFS(TablaGastos[Pago],TablaGastos[Semana],U7) -> 392382.67 | Y7: 2-Dic | AA7: 6-Abr | AB7: =SUMIF($Y$2:$Y$30,$AA7,$V$2:$V$30) -> 1382415.3 | AC7: =SUMIF($Y$2:$Y$30,$AA7,$W$2:$W$30) -> 92750 | AD7: =SUMIF($Y$2:$Y$30,$AA7,$X$2:$X$30) -> 1198456.7 | AE7: =SUMIFS(TablaGastos[Pendiente],TablaGastos[Mes],$AA7) -> 543865.2 | AF7: =AB7-AC7-AD7 -> 91208.6 | AH7: =AA7 -> 6-Abr | AI7: =AD7 -> 1198456.7 | AJ7: =AE7 -> 543865.2 | AL7: 5-Mar | AM7: 29668.1 | AN7: 0 | AP7: 614677.14 | AQ7: 132560.41 | AS7: 32961.384 | AT7: 809867.03
A8: 07 21-27 Dic | B8: 594544.75 | C8: 119136.08 | F8: Servicios | G8: 267089.42 | J8: AVV (MONARCA) | K8: 50000 | N8: OMAR GUERRERO | O8: 185800 | R8: LAR/Otros | S8: 2729 | U8: 21-27 Dic | V8: ='21-27 Dic'!H11 -> 595026.8 | W8: 0 | X8: =SUMIFS(TablaGastos[Pago],TablaGastos[Semana],U8) -> 594544.75 | Y8: 2-Dic | AA8: 7-May | AB8: =SUMIF($Y$2:$Y$30,$AA8,$V$2:$V$30) -> 1064879.8 | AC8: =SUMIF($Y$2:$Y$30,$AA8,$W$2:$W$30) -> 82050 | AD8: =SUMIF($Y$2:$Y$30,$AA8,$X$2:$X$30) -> 1037132.1 | AE8: =SUMIFS(TablaGastos[Pendiente],TablaGastos[Mes],$AA8) -> 1019588.4 | AF8: =AB8-AC8-AD8 -> -54302.284 | AH8: =AA8 -> 7-May | AI8: =AD8 -> 1037132.1 | AJ8: =AE8 -> 1019588.4 | AL8: 6-Abr | AM8: 227823.73 | AN8: 63929.13 | AP8: 811856.43 | AQ8: 9159.56 | AR8: 18768 | AS8: 66919.83 | AT8: 1198456.7
A9: 08 29 Dic 03 Ene | B9: 170659.6 | C9: 96136.08 | F9: Total general | G9: 7051503.6 | J9: AVV (PAGO MONARCA) | K9: 260435 | N9: ALEX Y RAFA | O9: 184999.8 | U9: 29 Dic 03 Ene | V9: ='29 Dic 03 Ene'!H11 -> 198000 | W9: 0 | X9: =SUMIFS(TablaGastos[Pago],TablaGastos[Semana],U9) -> 170659.6 | Y9: 2-Dic | AL9: 7-May | AM9: 215479.03 | AN9: 65367.8 | AO9: 2729 | AP9: 673111.09 | AQ9: 18269 | AS9: 62176.164 | AT9: 1037132.1
A10: 09 05 10 Ene | B10: 171923.65 | C10: 121136.08 | J10: AVV (PAGO SANTANDER) | K10: 280000 | N10: PATAGONIA CAJA CARTON y 30 lbs | O10: 153555 | U10: 05 10 Ene | V10: ='05 10 Ene'!H11 -> 221544.8 | W10: 0 | X10: =SUMIFS(TablaGastos[Pago],TablaGastos[Semana],U10) -> 171923.65 | Y10: 3-Ene | AL10: Total general | AM10: 742050.47 | AN10: 186766.93 | AO10: 2729 | AP10: 4909233.7 | AQ10: 837866.08 | AR10: 105768 | AS10: 267089.42 | AT10: 7051503.6
A11: 10 11 17 Ene | B11: 83200 | C11: 298963.54 | J11: AVV (PAGO SANTANDERT) | K11: 83200 | N11: Honorarios contador | O11: 146100.82 | U11: 11 17 Ene | V11: ='11 17 Ene'!H11 -> 299468.28 | W11: 0 | X11: =SUMIFS(TablaGastos[Pago],TablaGastos[Semana],U11) -> 83200 | Y11: 3-Ene
A12: 11 19 24 Ene | B12: 147580.56 | C12: 96247.8 | J12: AVV MONARCA | K12: 11000 | N12: CAJA CARTON (PATAGONIA) 20 y 30 lbs | O12: 127147.6 | U12: 19 24 Ene | V12: ='19 24 Ene'!H11 -> 165824 | W12: 0 | X12: =SUMIFS(TablaGastos[Pago],TablaGastos[Semana],U12) -> 147580.56 | Y12: 3-Ene
A13: 12 26 31 Ene | B13: 202978 | C13: 266885.8 | J13: BATAS, DIESEL, HOMEDEPOT | K13: 4674 | N13: CAJA RUTH GDL | O13: 97328.91 | U13: 26 31 Ene | V13: ='26 31 Ene'!H11 -> 321376 | W13: 0 | X13: =SUMIFS(TablaGastos[Pago],TablaGastos[Semana],U13) -> 202978 | Y13: 3-Ene
A14: 13 01 07 Feb | B14: 228558 | C14: 208253.8 | J14: Bolsa (Chavinda) | K14: 0 | U14: 01 07 Feb | V14: ='01 07 Feb'!H11 -> 249424 | W14: 0 | X14: =SUMIFS(TablaGastos[Pago],TablaGastos[Semana],U14) -> 228558 | Y14: 4-Feb
A15: 14 09 14 Feb | B15: 210551.15 | C15: 238665.44 | J15: BOLSA 30 LBS CHAVINDA | K15: 32500 | U15: 09 14 Feb | V15: ='09 14 Feb'!H11 -> 300680 | W15: 0 | X15: =SUMIFS(TablaGastos[Pago],TablaGastos[Semana],U15) -> 210551.15 | Y15: 4-Feb
A16: 15 16 21 Feb | B16: 205337.82 | C16: 376773.8 | J16: Bolsa Transparente (Chavinda) | K16: 8000 | U16: 16 21 Feb | V16: ='16 21 Feb'!H11 -> 437300 | W16: 0 | X16: =SUMIFS(TablaGastos[Pago],TablaGastos[Semana],U16) -> 205337.82 | Y16: 4-Feb
A17: 16 23 28 Feb | B17: 200467.6 | C17: 103500 | J17: CAJA CARTON (PATAGONIA) | K17: 62709.6 | U17: 23 28 Feb | V17: ='23 28 Feb'!I11 -> 227100 | W17: 0 | X17: =SUMIFS(TablaGastos[Pago],TablaGastos[Semana],U17) -> 200467.6 | Y17: 4-Feb
A18: 17 02 07 Mar | B18: 205104.2 | C18: 244546.17 | J18: CAJA CARTON (PATAGONIA) 20 y 30 lbs | K18: 127147.6 | U18: 02 07 Mar | V18: ='02 07 Mar'!I11 -> 328790 | W18: 0 | X18: =SUMIFS(TablaGastos[Pago],TablaGastos[Semana],U18) -> 205104.2 | Y18: 5-Mar
A19: 18 09-14 Mar | B19: 187131.92 | C19: 122064.87 | J19: CAJA CARTON (RUTH) | K19: 0 | U19: 09-14 Mar | V19: ='09-14 Mar'!I11 -> 328790 | W19: ='09-14 Mar'!I23 -> 22000 | X19: =SUMIFS(TablaGastos[Pago],TablaGastos[Semana],U19) -> 187131.92 | Y19: 5-Mar
A20: 19 16 21 Mar | B20: 66360.1 | C20: 266109.9 | J20: CAJA PATAGONI Y EMBAPACK | K20: 0 | U20: 16 21 Mar | V20: ='16 21 Mar'!I11 -> 328790 | W20: ='16 21 Mar'!I25 -> 18950 | X20: =SUMIFS(TablaGastos[Pago],TablaGastos[Semana],U20) -> 66360.1 | Y20: 5-Mar
A21: 20 23 28 Mar | B21: 203156.91 | C21: 113892.4 | J21: CAJA PATAGONIA | K21: 16800 | U21: 23 28 Mar | V21: ='23 28 Mar'!I11 -> 203456 | W21: ='23 28 Mar'!I25 -> 16950 | X21: =SUMIFS(TablaGastos[Pago],TablaGastos[Semana],U21) -> 203156.91 | Y21: 5-Mar
A22: 21 30 Mar 04 Abril | B22: 148113.9 | C22: 153892.4 | J22: CAJA RUTH GDL | K22: 97328.91 | U22: 30 Mar 04 Abril | V22: ='30 Mar 04 Abril'!I11 -> 132880 | W22: ='30 Mar 04 Abril'!I23 -> 17950 | X22: =SUMIFS(TablaGastos[Pago],TablaGastos[Semana],U22) -> 148113.9 | Y22: 5-Mar
A23: 22 06 11 Abril | B23: 132365.92 | C23: 153892.4 | J23: CAJA RUTH GDLMK BOXES | K23: 61642.4 | U23: 06 11 Abril | V23: ='06 11 Abril'!I11 -> 199760 | W23: ='06 11 Abril'!I23 -> 21950 | X23: =SUMIFS(TablaGastos[Pago],TablaGastos[Semana],U23) -> 132365.92 | Y23: 6-Abr
A24: 23 13 18 Abril | B24: 210849.13 | C24: 281703.18 | J24: CHRISTIAN MANUEL (TAMINAS) | K24: 1044 | U24: 13 18 Abril | V24: ='13 18 Abril'!I12 -> 323806.08 | W24: ='13 18 Abril'!I24 -> 20000 | X24: =SUMIFS(TablaGastos[Pago],TablaGastos[Semana],U24) -> 210849.13 | Y24: 6-Abr
A25: 24 20 25 Abril | B25: 541297.31 | C25: 55669.42 | J25: CIELO (TARIMAS) | K25: 8120 | U25: 20 25 Abril | V25: ='20 25 Abril'!J12 -> 524873.2 | W25: ='20 25 Abril'!J24 -> 31050 | X25: =SUMIFS(TablaGastos[Pago],TablaGastos[Semana],U25) -> 541297.31 | Y25: 6-Abr
A26: 25 27 Abril 02 Mayo | B26: 313944.32 | C26: 52600.2 | J26: CIELO ALEJANDRA (TARIMAS) GONZALO | K26: 0 | U26: 27 Abril 02 Mayo | V26: ='27 Abril 02 Mayo'!I13 -> 333976 | W26: ='27 Abril 02 Mayo'!I24 -> 19750 | X26: =SUMIFS(TablaGastos[Pago],TablaGastos[Semana],U26) -> 313944.32 | Y26: 6-Abr
A27: 26 04 09 Mayo | B27: 180013.84 | C27: 112478.9 | J27: CIPSA | K27: 23748 | U27: 04 09 Mayo | V27: ='04 09 Mayo'!I13 -> 193267.8 | W27: ='04 09 Mayo'!I25 -> 18850 | X27: =SUMIFS(TablaGastos[Pago],TablaGastos[Semana],U27) -> 180013.84 | Y27: 7-May
A28: 27 11 16 Mayo | B28: 355975.32 | C28: 311948.59 | J28: CIPSA (Control de Plagas) | K28: 0 | U28: 11 16 Mayo | V28: ='11 16 Mayo'!H13 -> 353464 | W28: ='11 16 Mayo'!H26 -> 19450 | X28: =SUMIFS(TablaGastos[Pago],TablaGastos[Semana],U28) -> 355975.32 | Y28: 7-May
A29: 28 18 23 Mayo | B29: 186422.02 | C29: 331571.09 | J29: CIRAM | K29: 7590.03 | U29: 18 23 Mayo | V29: ='18 23 Mayo'!I13 -> 206448 | W29: ='18 23 Mayo'!I26 -> 23500 | X29: =SUMIFS(TablaGastos[Pago],TablaGastos[Semana],U29) -> 186422.02 | Y29: 7-May
A30: 29 25 30 Mayo | B30: 314720.91 | C30: 263589.84 | J30: CODICE | K30: 3981.94 | U30: 25 30 Mayo | V30: ='25 30 Mayo'!J13 -> 311700 | W30: ='25 30 Mayo'!J27 -> 20250 | X30: =SUMIFS(TablaGastos[Pago],TablaGastos[Semana],U30) -> 314720.91 | Y30: 7-May
A31: Total general | B31: 7051503.6 | C31: 5246593.9 | J31: CODICE ETIQUETAS | K31: 4172.11 | U31: TOTAL | V31: =SUM(V2:V30) -> 8487715.8 | W31: =SUM(W2:W30) -> 306450 | X31: =SUM(X2:X30) -> 7051503.6
J32: COMPRA LAPTOP | K32: 7499
J33: Contador Carlos | K33: 10000
J34: Contador Raymundo | K34: 0
J35: Contador Reymundo | K35: 2000
J36: CONTRATO REIMER (Lic Carlos) | K36: 9280
J37: CONVENIO IMSS CXM | K37: 0
J38: Cristian Ramirez | K38: 95700
J39: DELFIN | K39: 0
J40: DEPACHO GARNICA | K40: 35904.6
J41: DEPACHO GARNICA (Pago Febrero 2026) | K41: 0
J42: DIKEN | K42: 3483.27
J43: Edgar Joel Vega Martínez (Emplaye) | K43: 14344.47
... J119: Total general | K119: 7051503.6

Sheet BD Gastos
A1: Orden | B1: Semana | C1: Concepto | D1: Categoría | E1: Pago | F1: Pendiente | G1: Periodo | H1: Mes
A2: 1 | B2: 10-15 NOV | C2: NOMINA FV | D2: Nómina/Personal | E2: 130000 | F2: 0 | G2: =TEXT(TablaGastos[[#This Row],[Orden]],"00")&" "&TablaGastos[[#This Row],[Semana]] -> 01 10-15 NOV | H2: =_xlfn.XLOOKUP(TablaGastos[[#This Row],[Semana]],Pivots!$U$2:$U$30,Pivots!$Y$2:$Y$30) -> 1-Nov
A3: 1 | B3: 10-15 NOV | C3: RAISA | D3: Nómina/Personal | E3: 50000 | F3: 0 | G3: =TEXT(TablaGastos[[#This Row],[Orden]],"00")&" "&TablaGastos[[#This Row],[Semana]] -> 01 10-15 NOV | H3: =_xlfn.XLOOKUP(TablaGastos[[#This Row],[Semana]],Pivots!$U$2:$U$30,Pivots!$Y$2:$Y$30) -> 1-Nov
A4: 1 | B4: 10-15 NOV | C4: PLATANO | D4: Producto/Fruta | E4: 37000 | F4: 0 | G4: =TEXT(TablaGastos[[#This Row],[Orden]],"00")&" "&TablaGastos[[#This Row],[Semana]] -> 01 10-15 NOV | H4: =_xlfn.XLOOKUP(TablaGastos[[#This Row],[Semana]],Pivots!$U$2:$U$30,Pivots!$Y$2:$Y$30) -> 1-Nov
A5: 1 | B5: 10-15 NOV | C5: ARTURO GUERRERO | D5: Nómina/Personal | E5: 30000 | F5: 0 | G5: =TEXT(TablaGastos[[#This Row],[Orden]],"00")&" "&TablaGastos[[#This Row],[Semana]] -> 01 10-15 NOV | H5: =_xlfn.XLOOKUP(TablaGastos[[#This Row],[Semana]],Pivots!$U$2:$U$30,Pivots!$Y$2:$Y$30) -> 1-Nov
A6: 1 | B6: 10-15 NOV | C6: ALEX Y RAFA | D6: Nómina/Personal | E6: 10000 | F6: 0 | G6: =TEXT(TablaGastos[[#This Row],[Orden]],"00")&" "&TablaGastos[[#This Row],[Semana]] -> 01 10-15 NOV | H6: =_xlfn.XLOOKUP(TablaGastos[[#This Row],[Semana]],Pivots!$U$2:$U$30,Pivots!$Y$2:$Y$30) -> 1-Nov
A7: 1 | B7: 10-15 NOV | C7: CIPSA | D7: Servicios | E7: 3000 | F7: 0 | G7: =TEXT(TablaGastos[[#This Row],[Orden]],"00")&" "&TablaGastos[[#This Row],[Semana]] -> 01 10-15 NOV | H7: =_xlfn.XLOOKUP(TablaGastos[[#This Row],[Semana]],Pivots!$U$2:$U$30,Pivots!$Y$2:$Y$30) -> 1-Nov
A8: 1 | B8: 10-15 NOV | C8: DEPACHO GARNICA | D8: Servicios | E8: 9000 | F8: 0 | G8: =TEXT(TablaGastos[[#This Row],[Orden]],"00")&" "&TablaGastos[[#This Row],[Semana]] -> 01 10-15 NOV | H8: =_xlfn.XLOOKUP(TablaGastos[[#This Row],[Semana]],Pivots!$U$2:$U$30,Pivots!$Y$2:$Y$30) -> 1-Nov
A9: 1 | B9: 10-15 NOV | C9: LORE | D9: Nómina/Personal | E9: 12006 | F9: 0 | G9: =TEXT(TablaGastos[[#This Row],[Orden]],"00")&" "&TablaGastos[[#This Row],[Semana]] -> 01 10-15 NOV | H9: =_xlfn.XLOOKUP(TablaGastos[[#This Row],[Semana]],Pivots!$U$2:$U$30,Pivots!$Y$2:$Y$30) -> 1-Nov
A10: 1 | B10: 10-15 NOV | C10: TARIMA | D10: Empaque/Material | E10: 0 | F10: 16240 | G10: =TEXT(TablaGastos[[#This Row],[Orden]],"00")&" "&TablaGastos[[#This Row],[Semana]] -> 01 10-15 NOV | H10: =_xlfn.XLOOKUP(TablaGastos[[#This Row],[Semana]],Pivots!$U$2:$U$30,Pivots!$Y$2:$Y$30) -> 1-Nov
A11: 1 | B11: 10-15 NOV | C11: SIMA (CALIBRACION) | D11: Servicios | E11: 0 | F11: 2500 | G11: =TEXT(TablaGastos[[#This Row],[Orden]],"00")&" "&TablaGastos[[#This Row],[Semana]] -> 01 10-15 NOV | H11: =_xlfn.XLOOKUP(TablaGastos[[#This Row],[Semana]],Pivots!$U$2:$U$30,Pivots!$Y$2:$Y$30) -> 1-Nov
A12: 1 | B12: 10-15 NOV | C12: NOMINA CXM | D12: Nómina/Personal | E12: 30000 | F12: 0 | G12: =TEXT(TablaGastos[[#This Row],[Orden]],"00")&" "&TablaGastos[[#This Row],[Semana]] -> 01 10-15 NOV | H12: =_xlfn.XLOOKUP(TablaGastos[[#This Row],[Semana]],Pivots!$U$2:$U$30,Pivots!$Y$2:$Y$30) -> 1-Nov
A13: 2 | B13: 17-22 NOV | C13: NOMINA FV | D13: Nómina/Personal | E13: 115000 | F13: 0 | G13: =TEXT(TablaGastos[[#This Row],[Orden]],"00")&" "&TablaGastos[[#This Row],[Semana]] -> 02 17-22 NOV | H13: =_xlfn.XLOOKUP(TablaGastos[[#This Row],[Semana]],Pivots!$U$2:$U$30,Pivots!$Y$2:$Y$30) -> 1-Nov
... A473: 29 | B473: 25 30 Mayo | C473: IMPUESTOS LAR | D473: Impuestos | E473: 13428 | F473: 0 | G473: =TEXT(TablaGastos[[#This Row],[Orden]],"00")&" "&TablaGastos[[#This Row],[Semana]] -> 29 25 30 Mayo | H473: =_xlfn.XLOOKUP(TablaGastos[[#This Row],[Semana]],Pivots!$U$2:$U$30,Pivots!$Y$2:$Y$30) -> 7-May
A474: Total | E474: =SUBTOTAL(109,TablaGastos[Pago]) -> 7051503.6 | F474: =SUBTOTAL(109,TablaGastos[Pendiente]) -> 5246593.9

Sheet 10-15 NOV
B1: GASTOS DE LA SEMANA | I1: RESUMEN — Nov 25
I2: Pagado | J2: =C20 -> 311006
I3: Pendiente | J3: =D20 -> 18740
I4: Ingresos | J4: =G11 -> 303500.8
B5: CONCEPTO | C5: PAGO | D5: PENDIENTE | I5: Egresos | J5: 0
B6: Semana del 17 al 22 de Noviembre | I6: Balance (Ing−Pag−Eg) | J6: =J4-J5-J2 -> -7505.2
B7: NOMINA FV | C7: 130000 | F7: EFECTIVO | G7: 80000
B8: RAISA | C8: 50000 | F8: OMAR GUERRERO | G8: 175500.8
B9: PLATANO | C9: 37000 | F9: GERA ARMENTA
B10: ARTURO GUERRERO | C10: 30000 | F10: CUENTA | G10: 48000
B11: ALEX Y RAFA | C11: 10000 | G11: =SUM(G7:G10) -> 303500.8
B12: CIPSA | C12: 3000
B13: DEPACHO GARNICA | C13: 9000
B14: LORE | C14: 12006
B15: TARIMA | D15: 16240
B16: SIMA (CALIBRACION) | D16: 2500
B17: NOMINA CXM | C17: 30000
C20: =SUM(C7:C19) -> 311006 | D20: =SUM(D7:D19) -> 18740
B23: OTROS GASTOS
B24: PLATANO 1A RECEPCION (12/11/25) | C24: 1906.7 | D24: KG
B25: PLATANO 2A RECEPCION (14/11/25) | C25: 5253.25 | D25: KG
B26: SUMA | C26: =SUM(C24:C25) -> 7159.95
B27: SE FACTURO Y PAGO | C27: 2000
B28: SALDO KG | C28: =C26-C27 -> 5159.95
C29: =C28*7.5 -> 38699.625

Sheet 17-22 NOV
B1: GASTOS DE LA SEMANA | I1: RESUMEN — Nov 25
I2: Pagado | J2: =C27 -> 292000
I3: Pendiente | J3: =D27 -> 186222
I4: Ingresos | J4: =G11 -> 295000
B5: CONCEPTO | C5: PAGO | D5: PENDIENTE | I5: Egresos | J5: 0
B6: Semana del 17 al 22 de Noviembre | I6: Balance (Ing−Pag−Eg) | J6: =J4-J5-J2 -> 3000
B7: NOMINA FV | C7: 115000 | F7: EFECTIVO | G7: 130000
B8: RAISA | C8: 30000 | F8: OMAR GUERRERO
B9: RAISA | D9: 50136 | F9: GERA ARMENTA | G9: 105000
B10: ARTURO GUERRERO | C10: 50000 | F10: CUENTA | G10: 60000
B11: ALEX Y RAFA | C11: 20000 | G11: =SUM(G7:G10) -> 295000
B12: CIPSA | C12: 3000
B13: DEPACHO GARNICA | C13: 9000
B14: LORE | D14: 12006
B15: TARIMA | D15: 16240
B16: SIMA (CALIBRACION) | D16: 2500
B17: NOMINA CXM | C17: 30000
B18: ROBERTO REYES | D18: 20300
B19: SINDULFO | D19: 20000
B20: SR IGNACIO | C20: 20000
B21: LALO AGUIRRE
B22: CIELO (TARIMAS) | D22: 16240
B23: Ing Aguilar , embolsadora | C23: 15000
B24: Contador Raymundo | D24: 3000
B25: EFECTIVO | D25: 20000
B26: Cristian Ramirez | D26: 25800
C27: =SUM(C7:C26) -> 292000 | D27: =SUM(D7:D26) -> 186222

Sheet 24-29 NOV
B1: GASTOS DE LA SEMANA | L1: RESUMEN — Nov 25
L2: Pagado | M2: =C28 -> 140470
L3: Pendiente | M3: =D28 -> 124800
L4: Ingresos | M4: =G11 -> 138000
B5: CONCEPTO | C5: PAGO | D5: PENDIENTE | L5: Egresos | M5: =J18 -> 12950
B6: Semana del 17 al 22 de Noviembre | F6: INGRESOS | L6: Balance (Ing−Pag−Eg) | M6: =M4-M5-M2 -> -15420
B7: NOMINA FV | C7: 110000 | F7: EFECTIVO | G7: 86000
B8: RAISA | F8: CUENTA | G8: 40000
B9: RAISA | D9: CÁLCULOS | F9: gaby | G9: 12000
B10: ARTURO GUERRERO | D10: 50000
B11: ALEX Y RAFA | D11: 20000 | G11: =SUM(G7:G9) -> 138000
B12: CIPSA | D12: 3000
B13: DEPACHO GARNICA | D13: 9000 | I13: EGRESOS
B14: LORE | I14: TATA | J14: 4000
B15: TARIMA | I15: CHURRAS | J15: 4000
B16: SIMA (CALIBRACION) | D16: 2500 | I16: GUSTAVO | J16: 3000
B17: NOMINA CXM | C17: 13000 | I17: VERO | J17: 1950
B18: ROBERTO REYES | D18: 20300 | J18: =SUM(J14:J17) -> 12950
B19: SINDULFO | D19: 20000
B20: SR IGNACIO
B21: LALO AGUIRRE
B22: CIELO (TARIMAS)
B23: Ing Aguilar , embolsadora
B24: Contador Raymundo
B25: EFECTIVO
B26: Cristian Ramirez
B27: Tenencias | C27: 17470
C28: =SUM(C7:C27) -> 140470 | D28: =SUM(D7:D27) -> 124800
B33: TENENCIA
B34: Tenencia
B35: * Honda CRV | C35: 1159 | D35: CHEQUE
B36: * CX-7 | C36: 3499 | D36: CHEQUE
B37: * Aveo | C37: 3499 | D37: CHEQUE
B38: * Ford Roja | C38: 2327 | D38: CHEQUE
C39: =SUM(C35:C38) -> 10484
B40: OTROS GASTOS
B41: FV H100 | C41: 3493
B42: GRUA | C42: 3493
C43: =SUM(C41:C42) -> 6986
C45: =C39+C43 -> 17470
C47: 40000
C48: =C45-C47 -> -22530

Sheet 01-06 Dic
B1: GASTOS DE LA SEMANA | P1: RESUMEN — Dic 25
P2: Pagado | Q2: =C29 -> 207784
P3: Pendiente | Q3: =D29 -> 74150
P4: Ingresos | Q4: =H11 -> 138000
B5: CONCEPTO | C5: PAGO | D5: PENDIENTE | P5: Egresos | Q5: =K18 -> 12950
B6: Semana del 01 al 06 de Diciembre | G6: INGRESOS | P6: Balance (Ing−Pag−Eg) | Q6: =Q4-Q5-Q2 -> -82734
B7: NOMINA FV | C7: 120000 | G7: EFECTIVO | H7: 86000
B8: RAISA | G8: CUENTA | H8: 40000
B9: EMBAPACK | G9: gaby | H9: 12000
B10: ARTURO GUERRERO | C10: 50000
B11: ALEX Y RAFA | C11: 10000 | H11: =SUM(H7:H9) -> 138000
B12: CIPSA | C12: 2784 | D12: 3000
B13: DEPACHO GARNICA | D13: 9000 | J13: EGRESOS | M13: OTROS GASTOS
B14: LORE | J14: TATA | K14: 4000 | M14: Churras | N14: =4000 -> 4000
B15: TARIMA | J15: CHURRAS | K15: 4000 | M15: TATA | N15: =4000 -> 4000
B16: SIMA (CALIBRACION) | D16: 2500 | J16: GUSTAVO | K16: 3000 | M16: Vero | N16: 1950
B17: NOMINA CXM | C17: =4000+4000+2000+3000+2000 -> 15000 | J17: VERO | K17: 1950 | M17: Gus | N17: 3000
B18: ROBERTO REYES | D18: 20300 | K18: =SUM(K14:K17) -> 12950 | M18: Gus gastos | N18: 2050
B19: SINDULFO | D19: 20000 | N19: =SUM(N14:N18) -> 15000
B20: SR IGNACIO | H20: NOTAS / PENDIENTES
B21: LALO AGUIRRE | H21: Pago CIPSA | M21: OTROS GASTOS
B22: CIELO (TARIMAS) | H22: Mandar al club x el refrigerador y snack | N22: 135000
B23: Ing Aguilar , embolsadora | H23: Llevar cartón a vender | N23: 80000
B24: Contador Carlos | C24: =250000*0.04 -> 10000 | H24: Ver con Gus y churras comida de los perros | N24: =N22-N23 -> 55000
B25: EFECTIVO | H25: TRANSPORTE Gente | M25: Viaje de Gente | N25: 12000
B26: Cristian Ramirez | M26: Cipsa | N26: 2784
B27: Bolsa Transparente (Chavinda) | D27: =7*1050 -> 7350 | N27: =N24-N25-N26 -> 40216
B28: Transporte de Gente | D28: 12000
C29: =SUM(C7:C27) -> 207784 | D29: =SUM(D7:D28) -> 74150 | H29: =15*30 -> 450 | N29: 78000
H30: = | N30: 40000
N31: =SUM(N29:N30) -> 118000
B34: TENENCIA
B35: Tenencia | E35: NOTAS / PENDIENTES
B36: * Honda CRV | C36: 1159 | E36: CHEQUE
B37: * CX-7 | C37: 3499 | E37: CHEQUE
B38: * Aveo | C38: 3499 | E38: CHEQUE
B39: * Ford Roja | C39: 2327 | E39: CHEQUE
C40: =SUM(C36:C39) -> 10484
B41: OTROS GASTOS
B42: FV H100 | C42: 3493
B43: GRUA | C43: 3493
C44: =SUM(C42:C43) -> 6986
C46: =C40+C44 -> 17470
C48: 40000
C49: =C46-C48 -> -22530

Sheet 08-13 Dic
B1: GASTOS DE LA SEMANA | P1: RESUMEN — Dic 25
P2: Pagado | Q2: =C28 -> 446604
P3: Pendiente | Q3: =D28 -> 294012.05
P4: Ingresos | Q4: =H11 -> 446470
B5: CONCEPTO | C5: PAGO | D5: PENDIENTE | P5: Egresos | Q5: =H20 -> 16950
B6: Semana del 08 al 13 de Diciembre | C6: PAGO | D6: PENDIENTE | G6: ENTRADAS | P6: Balance (Ing−Pag−Eg) | Q6: =Q4-Q5-Q2 -> -17084
B7: NOMINA FV | C7: 115000 | G7: EFECTIVO | H7: =70000-2250-4000-19000 -> 44750 | M7: INGRESOS
B8: RAISA | D8: 50000 | G8: proberry | H8: 199760 | M8: Miguel | N8: Compañero
B9: EMBAPACK | C9: 5000 | G9: proberry | H9: 201960 | L9: 2 kg Mango | M9: 150 | N9: 150
B10: ARTURO GUERRERO | D10: 50000 | L10: 1 kg Fresa | M10: 80 | N10: 80
B11: ALEX Y RAFA | C11: 10000 | H11: =SUM(H7:H9) -> 446470 | L11: 1 kg Frutos Rojos | M11: 100 | N11: 100
B12: CIPSA | D12: =2*2784 -> 5568 | G12: Diferencia | H12: =H11-C28 -> -134 | L12: Frambuesa | M12: 100
B13: DEPACHO GARNICA | D13: 9000 | L13: 48 Snack | M13: 480
B14: LORE (Transporte Personal) | D14: 12500 | G14: EGRESOS | M14: =SUM(M9:M13) -> 910 | N14: =SUM(N9:N12) -> 330
B15: SIMA (CALIBRACION) | D15: 2500 | G15: Soco | H15: 4000 | N15: =SUM(M14:N14) -> 1240
B16: NOMINA CXM | C16: =17000 -> 17000 | G16: TATA | H16: 4000
B17: ROBERTO REYES | D17: 49247.8 | G17: CHURRAS | H17: 4000
B18: SINDULFO | G18: GUSTAVO | H18: 3000
B19: SR IGNACIO | G19: VERO | H19: 1950
B20: LALO AGUIRRE | D20: 22846.25 | H20: =SUM(H15:H19) -> 16950
B21: CIELO (TARIMAS)
B22: Ing Aguilar , embolsadora
B23: EFECTIVO
B24: Cristian Ramirez
B25: Bolsa Transparente (Chavinda) | D25: =7*1050 -> 7350
B26: CAJA CARTON (PATAGONIA) | C26: 19604
B27: AVV (PAGO SANTANDER) | C27: 280000 | D27: 85000
C28: =SUM(C7:C27) -> 446604 | D28: =SUM(D7:D27) -> 294012.05
C30: =C27-365000 -> -85000

Sheet 15-20 Dic
B1: GASTOS DE LA SEMANA | J1: RESUMEN — Dic 25
J2: Pagado | K2: =C30 -> 392382.67
J3: Pendiente | K3: =D30 -> 159012.05
J4: Ingresos | K4: =H11 -> 381000
B5: CONCEPTO | C5: PAGO | D5: PENDIENTE | J5: Egresos | K5: =H20 -> 12950
B6: Semana del 15 al 20 de Diciembre | C6: PAGO | D6: PENDIENTE | G6: ENTRADAS | J6: Balance (Ing−Pag−Eg) | K6: =K4-K5-K2 -> -24332.67
B7: NOMINA FV | C7: 125038 | G7: EFECTIVO
B8: RAISA | D8: 50000 | G8: proberry | H8: 183000
B9: EMBAPACK | G9: proberry | H9: 198000
B10: ARTURO GUERRERO | C10: 50000
B11: ALEX Y RAFA | C11: 10000 | H11: =SUM(H7:H9) -> 381000
B12: CIPSA | D12: =2*2784 -> 5568 | G12: Diferencia | H12: =H11-C30 -> -11382.67
B13: DEPACHO GARNICA | D13: 9000
B14: LORE (Transporte Personal) | D14: 12500 | G14: EGRESOS
B15: SIMA (CALIBRACION) | D15: 2500 | G15: Soco
B16: NOMINA CXM | C16: 13000 | G16: TATA | H16: 4000
B17: ROBERTO REYES | D17: 49247.8 | G17: CHURRAS | H17: 4000
B18: SINDULFO | G18: GUSTAVO | H18: 3000
B19: SR IGNACIO | G19: VERO | H19: 1950
B20: LALO AGUIRRE | D20: 22846.25 | H20: =SUM(H15:H19) -> 12950
B21: CIELO (TARIMAS)
B22: Ing Aguilar , embolsadora | C22: 12000
B23: Honorarios contador | C23: =9219.5*1.04 -> 9588.28
B24: Cristian Ramirez | C24: 28500
B25: Cristian Ramirez | C25: 10200
B26: Bolsa Transparente (Chavinda) | C26: 8000 | D26: =7*1050 -> 7350
B27: CAJA CARTON (PATAGONIA) | C27: =19604*2 -> 39208
B28: ETIQUETAS CODICE | C28: =2507.91+1140.48 -> 3648.39
B29: AVV (PAGO SANTANDERT) | C29: =80000*1.04 -> 83200
C30: =SUM(C7:C29) -> 392382.67 | D30: =SUM(D7:D29) -> 159012.05

Sheet 21-27 Dic
B1: GASTOS DE LA SEMANA | M1: RESUMEN — Dic 25
M2: Pagado | N2: =C40 -> 594544.75
M3: Pendiente | N3: =D40 -> 119136.08
M4: Ingresos | N4: =H11 -> 595026.8
B5: CONCEPTO | C5: PAGO | D5: PENDIENTE | M5: Egresos | N5: 0
B6: Semana del 15 al 20 de Diciembre | C6: PAGO | D6: PENDIENTE | G6: ENTRADAS | M6: Balance (Ing−Pag−Eg) | N6: =N4-N5-N2 -> 482.05
B7: NOMINA FV | C7: 104223 | G7: EFECTIVO | H7: 1000 | K7: 337000
B8: NOMINA FV | C8: 20000 | G8: REIMER | H8: 400000
B9: RAISA | G9: Proberry | H9: 194026.8
B10: EMBAPACK | G10: OTROS GASTOS
B11: ARTURO GUERRERO | C11: 60000 | H11: =SUM(H7:H9) -> 595026.8
B12: ALEX Y RAFA | D12: 15000 | G12: Diferencia | H12: =H11-C40 -> 482.05
B13: CIPSA | C13: =2*2784 -> 5568 | H13: =H12-D40 -> -118654.03
B14: DEPACHO GARNICA | G14: OTROS GASTOS
B15: LORE (Transporte Personal) | G15: Soco | H15: 4000
B16: SIMA (CALIBRACION) | D16: 2500 | G16: TATA | H16: 4000
B17: NOMINA CXM | C17: 20852.5 | G17: CHURRAS | H17: 4000
B18: ROBERTO REYES | D18: 49247.8 | G18: GUSTAVO | H18: 3000
B19: SINDULFO | G19: VERO | H19: 1950
B20: SR IGNACIO
B21: LALO AGUIRRE | C21: 22846.25
B22: CIELO (TARIMAS) | C22: 8120 | H22: =SUM(H15:H21) -> 16950
B23: Ing Aguilar , embolsadora | D23: 12000
B24: Honorarios contador | D24: 9588.28 | G24: OTROS GASTOS
B25: Cristian Ramirez | D25: 22800 | G25: FV | H25: 115000
B26: Cristian Ramirez | C26: 28500 | G26: CXM | H26: =H22 -> 16950
B27: Bolsa Transparente (Chavinda) | D27: 8000 | H27: =SUM(H25:H26) -> 131950
B28: CAJA CARTON (PATAGONIA)
B29: ETIQUETAS CODICE | G29: EFECTIVO | H29: 95000
B30: AVV (PAGO MONARCA) | C30: =138229+122206 -> 260435 | G30: EFECTIVO | H30: 20000
B31: telefono | C31: 12000 | H31: =SUM(H29:H30) -> 115000
B32: GUAYABAS LA ESPERANZA | C32: 50000 | H32: =H27-H31 -> 16950
B33: CONTRATO REIMER (Lic Carlos)
B34: Contador Reymundo | C34: 2000
B35: FACTURA E IMPUESTOS LAR
B36: IMSS CXM
B37: PAGO CONTPAQ | H37: =220000*1.04 -> 228800
C40: =SUM(C7:C39) -> 594544.75 | D40: =SUM(D7:D39) -> 119136.08
B42: OTROS GASTOS
B43: REIMER
B44: Filtros | C44: 780
B45: Aceite (2 galones) | C45: 800
B46: Mano Obra Mecanico | C46: 1500
B47: Refacciones Electrico | C47: 1000
B48: Mano Obra Electrico | C48: 700
B49: Dia del Churras | C49: 600
C50: =SUM(C44:C49) -> 5380

Sheet 29 Dic 03 Ene
B1: GASTOS DE LA SEMANA | M1: RESUMEN — Dic 25
M2: Pagado | N2: =C40 -> 191619.6
M3: Pendiente | N3: =D40 -> 96136.08
M4: Ingresos | N4: =H11 -> 198000
B5: CONCEPTO | C5: PAGO | D5: PENDIENTE | M5: Egresos | N5: 0
B6: Semana del 15 al 20 de Diciembre | C6: PAGO | D6: PENDIENTE | G6: ENTRADAS | M6: Balance (Ing−Pag−Eg) | N6: =N4-N5-N2 -> 6380.4
B7: NOMINA FV | C7: 125037 | K7: 337000
B8: NOMINA FV | G8: proberry | H8: 198000
B9: RAISA
B10: EMBAPACK | G10: OTROS GASTOS
B11: ARTURO GUERRERO | H11: =SUM(H7:H8) -> 198000
B12: ALEX Y RAFA | C12: 10000 | G12: Diferencia | H12: =H11-C40 -> 6380.4
B13: CIPSA | H13: =H12-D40 -> -89755.68
B14: DEPACHO GARNICA | G14: OTROS GASTOS
B15: LORE (Transporte Personal) | C15: 7308 | G15: Soco | H15: 4000
B16: SIMA (CALIBRACION) | D16: 2500 | G16: TATA | H16: 4000
B17: NOMINA CXM | G17: CHURRAS | H17: 4000
B18: ROBERTO REYES | D18: 49247.8 | G18: GUSTAVO | H18: 3000
B19: SINDULFO | G19: VERO | H19: 1950
B20: SR IGNACIO
B21: LALO AGUIRRE
B22: CIELO (TARIMAS) | H22: =SUM(H15:H21) -> 16950
B23: Ing Aguilar , embolsadora | D23: 12000
B24: Honorarios contador | D24: 9588.28 | G24: OTROS GASTOS
B25: Cristian Ramirez | D25: 22800 | G25: FV | H25: 115000
B26: Cristian Ramirez | G26: CXM | H26: =H22 -> 16950
B27: Bolsa Transparente (Chavinda) | H27: =SUM(H25:H26) -> 131950
B28: CAJA CARTON (PATAGONIA)
B29: ETIQUETAS CODICE | G29: EFECTIVO | H29: 95000
B30: AVV (PAGO MONARCA) | G30: EFECTIVO | H30: 20000
B31: CELULAR | H31: =SUM(H29:H30) -> 115000
B32: GUAYABAS LA ESPERANZA | H32: =H27-H31 -> 16950
B33: CONTRATO REIMER (Lic Carlos) | C33: 9280
B34: Contador Reymundo
B35: FACTURA E IMPUESTOS LAR | C35: =(225000*0.04)+(11500*1.04) -> 20960
B36: IMSS CXM | C36: 10000
B37: PAGO CONTPAQ | C37: 6020.4 | H37: =220000*1.04 -> 228800
B38: Primus Lab | C38: 3014.2
C40: =SUM(C7:C39) -> 191619.6 | D40: =SUM(D7:D39) -> 96136.08
B42: OTROS GASTOS
B43: REIMER
B44: Filtros | C44: 780
B45: Aceite (2 galones) | C45: 800
B46: Mano Obra Mecanico | C46: 1500
B47: Refacciones Electrico | C47: 1000
B48: Mano Obra Electrico | C48: 700
B49: Dia del Churras | C49: 600
C50: =SUM(C44:C49) -> 5380

Sheet 05 10 Ene
B1: GASTOS DE LA SEMANA | O1: RESUMEN — Ene 26
O2: Pagado | P2: =C39 -> 171923.65
O3: Pendiente | P3: =D39 -> 121136.08
O4: Ingresos | P4: =H11 -> 221544.8
B5: CONCEPTO | C5: PAGO | D5: PENDIENTE | O5: Egresos | P5: 0
B6: Semana del 05 al 10 de Enero | C6: PAGO | D6: PENDIENTE | G6: ENTRADAS | J6: ENTRADAS | O6: Balance (Ing−Pag−Eg) | P6: =P4-P5-P2 -> 49621.15
B7: NOMINA FV | C7: 95000 | H7: 53100 | K7: =9.08*90 -> 817.2 | L7: 65 | M7: =K7*L7 -> 53118
B8: NOMINA CXM | C8: =H22 -> 17800 | G8: Proberry a Cuenta | H8: 90000 | K8: A cuenta Nomina | M8: -15600
B9: RAISA | G9: Proberry barriles | H9: 78444.8 | M9: =SUM(M7:M8) -> 37518
B10: EMBAPACK
B11: ALEX Y RAFA | D11: 15000 | H11: =SUM(H7:H10) -> 221544.8
B12: CIPSA | G12: Diferencia | H12: =H11-C39 -> 49621.15
B13: DEPACHO GARNICA
B14: LORE (Transporte Personal) | G14: OTROS GASTOS
B15: SIMA (CALIBRACION) | G15: Soco | H15: 4000
B16: NOMINA CXM | D16: 2500 | G16: TATA | H16: 4000
B17: ROBERTO REYES | G17: CHURRAS | H17: 4000
B18: SINDULFO | D18: 49247.8 | G18: GUSTAVO | H18: 3000
B19: SR IGNACIO | G19: VERO | H19: 1950
B20: LALO AGUIRRE | G20: Brayan | H20: =500+350 -> 850
B21: CIELO (TARIMAS)
B22: Ing Aguilar , embolsadora | H22: =SUM(H15:H21) -> 17800
B23: Honorarios contador | D23: 12000
B24: Cristian Ramirez | D24: 9588.28
B25: Cristian Ramirez | D25: 22800
B26: Bolsa Transparente (Chavinda)
B27: CAJA CARTON (PATAGONIA)
B28: ETIQUETAS CODICE
B29: AVV (PAGO MONARCA)
B30: GUAYABAS LA ESPERANZA
B31: SANICHEM
B32: CODICE | C32: 3981.94
B33: DIKEN | C33: 2041.71
B34: IMSS CXM | D34: 10000
B35: PAGO CONTPAQ
B36: OMAR nomina | C36: 15600
B37: OMAR | C37: 37500
C39: =SUM(C7:C38) -> 171923.65 | D39: =SUM(D7:D38) -> 121136.08
B41: OTROS GASTOS
B42: REIMER
B43: Filtros | C43: 780
B44: Aceite (2 galones) | C44: 800
B45: Mano Obra Mecanico | C45: 1500
B46: Refacciones Electrico | C46: 1000
B47: Mano Obra Electrico | C47: 700
B48: Dia del Churras | C48: 600
C49: =SUM(C43:C48) -> 5380

Sheet 11 17 Ene
B1: GASTOS DE LA SEMANA | O1: RESUMEN — Ene 26
O2: Pagado | P2: =C39 -> 83200
O3: Pendiente | P3: =D39 -> 298963.54
O4: Ingresos | P4: =H11 -> 299468.28
B5: CONCEPTO | C5: PAGO | D5: PENDIENTE | O5: Egresos | P5: 0
B6: Semana del 05 al 10 de Enero | C6: PAGO | D6: PENDIENTE | G6: ENTRADAS | J6: ENTRADAS | O6: Balance (Ing−Pag−Eg) | P6: =P4-P5-P2 -> 216268.28
B7: NOMINA FV | C7: 73000 | D7: 22000 | G7: GALU | H7: =22000+16000+9000 -> 47000 | K7: =9.08*90 -> 817.2 | L7: 65 | M7: =K7*L7 -> 53118
B8: NOMINA CXM | C8: 10200 | D8: 14950 | G8: Proberry a Cuenta ( Pago por contador efectivo) | H8: =41612-(41612*0.04) -> 39947.52 | K8: A cuenta Nomina | M8: -15600
B9: RAISA | G9: Proberry barriles | H9: =103456-(103456*0.04) -> 99317.76 | M9: =SUM(M7:M8) -> 37518
B10: EMBAPACK | G10: Proberry barriles | H10: =82319+30884 -> 113203
B11: ALEX Y RAFA | D11: 15000 | H11: =SUM(H7:H10) -> 299468.28
B12: CIPSA | G12: Diferencia | H12: =H11-C39-D39 -> -82695.26
B13: DEPACHO GARNICA
B14: LORE (Transporte Personal)
B15: SIMA (CALIBRACION) | G15: Soco | H15: 4000
B16: ROBERTO REYES | G16: TATA | H16: 4000 | K16: OTROS GASTOS
B17: SINDULFO | D17: 49247.8 | G17: CHURRAS | H17: 4000 | K17: Nomina | L17: 22000
B18: SR IGNACIO | G18: GUSTAVO | H18: 3000 | K18: Caja 10 lbs | L18: 20000
B19: LALO AGUIRRE | G19: VERO | H19: 1950 | K19: Caja 30 lbs | L19: 13400
B20: CIELO (TARIMAS) | D20: 15660 | G20: Jair | H20: 2200 | L20: =SUM(L17:L19) -> 55400
B21: Ing Aguilar , embolsadora | G21: AVV | H21: 3000
B22: Honorarios contador | D22: =1664+4138 -> 5802 | G22: LAR | H22: 3000
B23: Cristian Ramirez | D23: 37000 | H23: =SUM(H15:H22) -> 25150
B24: Cristian Ramirez | G24: PENDIENTE
B25: Bolsa (Chavinda) | D25: 8460.6 | G25: Soco | H25: 6000 | L25: 0.048388768 | M25: Cielo Alejandra
B26: CAJA CARTON (PATAGONIA) | D26: =16.8*1.16*500 -> 9744 | G26: TATA | H26: 1000
B27: ETIQUETAS CODICE | G27: CHURRAS | H27: 1000
B28: AVV (PAGO MONARCA) | G28: GUSTAVO | H28: 1000
B29: GUAYABAS LA ESPERANZA | G29: VERO | H29: 1950
B30: SANICHEM | D30: 7389.2 | G30: Jair | J30: =SUM(H25:H29) -> 10950 | L30: =16.8*500*1.16 -> 9744
B31: TRANSPORTE LORE | D31: 9570 | G31: AVV | H31: 2000
B32: DELFIN | D32: 246.44 | G32: LAR | H32: 2000
B33: PROLIZA | D33: 593.5 | H33: =SUM(H25:H32) -> 14950
B34: IMPUESTOS OCTUBRE LAR | D34: 7900
B35: ADEUDO GALU | D35: 47000
B36: CAJA CARTON (RUTH) | D36: 20000
B37: CAJA CARTON (PATAGONIA) | D37: 13400
B38: CAJA PATAGONI Y EMBAPACK | D38: 15000
C39: =SUM(C7:C37) -> 83200 | D39: =SUM(D7:D38) -> 298963.54 | G39: CÁLCULOS
G40: 99300
G41: 27000
G42: =G40-G41 -> 72300
G43: 11000
G44: =G42-G43 -> 61300

Sheet 19 24 Ene
B1: GASTOS DE LA SEMANA | O1: RESUMEN — Ene 26
O2: Pagado | P2: =C39 -> 130780.56
O3: Pendiente | P3: =D39 -> 96247.8
O4: Ingresos | P4: =H11 -> 165824
B5: CONCEPTO | C5: PAGO | D5: PENDIENTE | O5: Egresos | P5: 0
B6: Semana del 05 al 10 de Enero | C6: PAGO | D6: PENDIENTE | G6: ENTRADAS | O6: Balance (Ing−Pag−Eg) | P6: =P4-P5-P2 -> 35043.44
B7: NOMINA FV | C7: 95000
B8: NOMINA CXM | C8: =H33 -> 25250 | G8: Proberry a Cuenta ( Pago por contador efectivo) | H8: 100000
B9: RAISA | G9: Proberry Zarzamora | H9: 65824
B10: EMBAPACK
B11: ALEX Y RAFA | H11: =SUM(H7:H10) -> 165824
B12: CIPSA | G12: Diferencia | H12: =H11-C39-D39 -> -61204.36
B13: DEPACHO GARNICA | L13: =9*60*13.6 -> 7344
B14: LORE (Transporte Personal) | G14: OTROS GASTOS | L14: =L13/150 -> 48.96
B15: SIMA (CALIBRACION) | G15: Soco | H15: 4000
B16: ROBERTO REYES | G16: TATA | H16: 4000
B17: SINDULFO | D17: 49247.8 | G17: CHURRAS | H17: 4000 | M17: del pago
B18: SR IGNACIO | G18: GUSTAVO | H18: 3000
B19: LALO AGUIRRE | G19: VERO | H19: 1950
B20: CIELO (TARIMAS) | G20: Jair | H20: =2200/6*4-150 -> 1316.6667
B21: Ing Aguilar , embolsadora | G21: AVV | H21: 3000
B22: Honorarios contador | C22: =H11*0.04 -> 6632.96 | G22: LAR | H22: 3000
B23: Cristian Ramirez | H23: =SUM(H15:H22) -> 24266.667
B24: Cristian Ramirez | G24: OTROS GASTOS
B25: Bolsa (Chavinda) | G25: Soco | H25: 4000
B26: CAJA CARTON (PATAGONIA) | G26: TATA | H26: 4000
B27: ETIQUETAS CODICE | G27: CHURRAS | H27: 4000
B28: AVV (PAGO MONARCA) | G28: GUSTAVO | H28: 3000
B29: GUAYABAS LA ESPERANZA | G29: VERO | H29: 1950
B30: SANICHEM | G30: Jair | H30: 1300
B31: TRANSPORTE LORE | G31: AVV | H31: 3500
B32: DELFIN | G32: LAR | H32: 3500
B33: PROLIZA | H33: =SUM(H25:H32) -> 25250
B34: IMPUESTOS OCTUBRE LAR
B35: ADEUDO GALU | D35: 47000
B36: CAJA CARTON (RUTH)
B37: CAJA CARTON (PATAGONIA) | C37: =16.8*200*1.16 -> 3897.6
B38: CAJA PATAGONIA | C38: =16.8*1000 -> 16800
C39: =SUM(C7:C37) -> 130780.56 | D39: =SUM(D7:D38) -> 96247.8 | G39: CÁLCULOS
G40: 99300
G41: 27000
G42: =G40-G41 -> 72300
G43: 11000
G44: =G42-G43 -> 61300

Sheet 26 31 Ene
B1: GASTOS DE LA SEMANA | O1: RESUMEN — Ene 26
O2: Pagado | P2: =C34 -> 202978
O3: Pendiente | P3: =D34 -> 266885.8
O4: Ingresos | P4: =H11 -> 321376
B5: CONCEPTO | C5: PAGO | D5: PENDIENTE | O5: Egresos | P5: 0
B6: Semana del 26 al 31 de Enero | C6: PAGO | D6: PENDIENTE | G6: ENTRADAS | O6: Balance (Ing−Pag−Eg) | P6: =P4-P5-P2 -> 118398
B7: NOMINA FV | C7: 120000
B8: NOMINA CXM | C8: =H23 -> 14950 | G8: Proberry a Cuenta ( Pago por contador efectivo) | H8: 117920
B9: RAISA | D9: 20000 | G9: Proberry Zarzamora | H9: 203456
B10: EMBAPACK
B11: ALEX Y RAFA | C11: 15000 | H11: =SUM(H7:H10) -> 321376
B12: CIPSA | G12: Diferencia | H12: =H11-C34-D34 -> -148487.8
B13: DEPACHO GARNICA | L13: =9*60*13.6 -> 7344
B14: LORE (Transporte Personal) | D14: 8526 | G14: OTROS GASTOS | L14: =L13/150 -> 48.96
B15: SIMA (CALIBRACION) | G15: Soco
B16: ROBERTO REYES | G16: TATA | H16: 4500
B17: SINDULFO | D17: 49247.8 | G17: GUSTAVO | H17: 3500 | M17: del pago
B18: embapack | D18: 2987 | G18: GUSTAVO gastos | H18: 2000
B19: LALO AGUIRRE | G19: VERO | H19: 1950
B20: CIELO (TARIMAS) | D20: 16240 | G20: Jair
B21: Ing Aguilar , embolsadora | D21: 35178 | G21: AVV | H21: 3000
B22: Honorarios contador | C22: =12392+834 -> 13226 | G22: LAR
B23: Cristian Ramirez | D23: 28500 | H23: =SUM(H15:H22) -> 14950
B24: Cristian Ramirez | D24: 25500 | H24: 9000
B25: ETIQUETAS CODICE | H25: =H23-H24 -> 5950
B26: gastos | D26: 10000
B27: GUAYABAS LA ESPERANZA
B28: SANICHEM | D28: 5007
B29: IMSS | C29: 30000 | D29: 10000
B30: ADEUDO GALU | D30: 47000
B31: BOLSA 30 LBS CHAVINDA | D31: =1450*6 -> 8700
B32: CAJA CARTON (PATAGONIA) 20 y 30 lbs | C32: =16.9*1.16*500 -> 9802 | D32: =E39 -> 0
B33: OTROS GASTOS
C34: =SUM(C7:C32) -> 202978 | D34: =SUM(D7:D33) -> 266885.8
C35: =H9-C34 -> 478
C36: Precio | D36: Cantidad | E36: Importe
B37: 20 lbs | C37: =15.75*1.16 -> 18.27 | D37: 9635
B38: 30 lbs | C38: =16.9*1.16 -> 19.604 | D38: 24724.8
D39: 32659.8
D40: =D39/16 -> 2041.2375
D41: =D40/30 -> 68.04125

Sheet 01 07 Feb
B1: GASTOS DE LA SEMANA | O1: RESUMEN — Feb 26
O2: Pagado | P2: =C34 -> 228558
O3: Pendiente | P3: =D34 -> 208253.8
O4: Ingresos | P4: =H11 -> 249424
B5: CONCEPTO | C5: PAGO | D5: PENDIENTE | O5: Egresos | P5: 0
B6: Semana del 02 al 07 Feb | C6: PAGO | D6: PENDIENTE | G6: ENTRADAS | O6: Balance (Ing−Pag−Eg) | P6: =P4-P5-P2 -> 20866
B7: NOMINA FV | C7: 110000 | G7: Proberry Zarzamora | H7: 40800
B8: NOMINA CXM | C8: =H23 -> 19950 | G8: Proberry ARANDANO | H8: 5168
B9: RAISA | C9: 29000 | G9: Proberry CRUMBLE | H9: 203456
B10: EMBAPACK
B11: ALEX Y RAFA | C11: 20000 | H11: =SUM(H7:H10) -> 249424
B12: CIPSA | G12: Diferencia | H12: =H11-C34-D34 -> -187387.8
B13: DEPACHO GARNICA | L13: =9*60*13.6 -> 7344
B14: LORE (Transporte Personal) | D14: 8526 | G14: OTROS GASTOS | L14: =L13/150 -> 48.96
B15: SIMA (CALIBRACION) | G15: Soco | H15: 4000
B16: ROBERTO REYES | G16: TATA | H16: 4000
B17: SINDULFO | D17: 49247.8 | G17: GUSTAVO | H17: 3000 | M17: del pago
B18: embapack | G18: GUSTAVO gastos
B19: LALO AGUIRRE | G19: VERO | H19: 1950
B20: CIELO (TARIMAS) | G20: AVV | H20: 3500
B21: Ing Aguilar , embolsadora | D21: 35178 | G21: LAR | H21: 3500
B22: Honorarios contador | C22: =4608+(20000*0.05) -> 5608
B23: Cristian Ramirez | D23: 28500 | H23: =SUM(H15:H22) -> 19950
B24: Cristian Ramirez
B25: ETIQUETAS CODICE
B26: CAJA RUTH GDL | C26: 44000
B27: GUAYABAS LA ESPERANZA
B28: SANICHEM
B29: IMSS | D29: 30000
B30: ADEUDO GALU | D30: 47000
B31: BOLSA 30 LBS CHAVINDA
B32: CAJA CARTON (PATAGONIA) 20 y 30 lbs | D32: =16.9*1.16*500 -> 9802
C34: =SUM(C7:C32) -> 228558 | D34: =SUM(D7:D33) -> 208253.8
C37: 112000
C38: =C8+C9+C11+C26 -> 112950

Sheet 09 14 Feb
B1: GASTOS DE LA SEMANA | O1: RESUMEN — Feb 26
O2: Pagado | P2: =C35 -> 210551.15
O3: Pendiente | P3: =D35 -> 238665.44
O4: Ingresos | P4: =H11 -> 300680
B5: CONCEPTO | C5: PAGO | D5: PENDIENTE | O5: Egresos | P5: 0
B6: Semana del 09 al 14 Feb | C6: PAGO | D6: PENDIENTE | G6: ENTRADAS | O6: Balance (Ing−Pag−Eg) | P6: =P4-P5-P2 -> 90128.85
B7: NOMINA FV | C7: 98000 | D7: 12500 | G7: Proberry 80/20 | H7: 190680
B8: NOMINA CXM | C8: =H23 -> 9950 | G8: Saldo LAR | H8: 30000
B9: RAISA | C9: 27783.47 | G9: Prestamo Embolsadora | H9: 80000
B10: RAISA | D10: 19105
B11: EMBAPACK | C11: 3940.45 | H11: =SUM(H7:H10) -> 300680
B12: ALEX Y RAFA | D12: 19999.8 | G12: Diferencia | H12: =H11-C35-D35 -> -148536.59
B13: CIPSA | L13: =9*60*13.6 -> 7344
B14: DEPACHO GARNICA | G14: OTROS GASTOS | L14: =L13/150 -> 48.96
B15: LORE (Transporte Personal) | D15: 8526 | G15: Soco
B16: SIMA (CALIBRACION) | G16: TATA | H16: 4500
B17: ROBERTO REYES | G17: GUSTAVO | H17: 3500 | M17: del pago
B18: SINDULFO | D18: 49247.8 | G18: GUSTAVO gastos
B19: LALO AGUIRRE | G19: VERO | H19: 1950
B20: CIELO (TARIMAS) | G20: AVV
B21: Ing Aguilar , embolsadora | D21: 35178 | G21: LAR
B22: Honorarios contador | C22: =(C7+D8)*0.04 -> 3920
B23: Cristian Ramirez | C23: 28500 | H23: =SUM(H15:H22) -> 9950
B24: Edgar Joel Vega Martínez (Emplaye) | C24: 2728.32
B25: ETIQUETAS CODICE
B26: CAJA RUTH GDL | C26: 33328.91 | D26: 9280
B27: GUAYABAS LA ESPERANZA
B28: SANICHEM
B29: IMSS | D29: 30000
B30: ADEUDO GALU | D30: 47000
B31: BOLSA 30 LBS CHAVINDA | D31: =1450*4 -> 5800
B32: CAJA CARTON (PATAGONIA) 20 y 30 lbs
B33: MARACUYA BORREGOS | C33: =6*400 -> 2400
B34: SEGURO AVEO | D34: 2028.84
C35: =SUM(C7:C34) -> 210551.15 | D35: =SUM(D7:D34) -> 238665.44
C38: 112000
C39: =D8+C9+E12+C26 -> 61112.38

Sheet 16 21 Feb
B1: GASTOS DE LA SEMANA | O1: RESUMEN — Feb 26
O2: Pagado | P2: =C36 -> 205337.82
O3: Pendiente | P3: =D36 -> 376773.8
O4: Ingresos | P4: =H11 -> 437300
B5: CONCEPTO | C5: PAGO | D5: PENDIENTE | O5: Egresos | P5: 0
B6: Semana del 16 al 21 Feb | C6: PAGO | D6: PENDIENTE | G6: ENTRADAS | O6: Balance (Ing−Pag−Eg) | P6: =P4-P5-P2 -> 231962.18
B7: NOMINA FV | C7: 110000 | D7: 110000 | G7: Proberry Crumble | H7: 198200
B8: NOMINA CXM | C8: =H23 -> 18750 | D8: 20000 | G8: Proberry Bloque Fram | H8: 39100
B9: RAISA | D9: 30000 | G9: Proberry 80/20 | H9: 200000
B10: RAISA
B11: EMBAPACK | C11: 5916 | H11: =SUM(H7:H10) -> 437300
B12: ALEX Y RAFA | C12: 19999.8 | D12: 10000 | G12: Diferencia | H12: =H11-C36-D36 -> -144811.62
B13: CIPSA | L13: =9*60*13.6 -> 7344
B14: DEPACHO GARNICA | G14: OTROS GASTOS | L14: =L13/150 -> 48.96
B15: LORE (Transporte Personal) | D15: 8526 | G15: Soco | H15: 4000
B16: SIMA (CALIBRACION) | G16: TATA | H16: 4000
B17: ROBERTO REYES | G17: GUSTAVO | H17: 3000 | M17: del pago
B18: SINDULFO | D18: 49247.8 | G18: GUSTAVO gastos
B19: LALO AGUIRRE | C19: 4045.02 | G19: VERO | H19: 1950
B20: CIELO (TARIMAS) | G20: AVV | H20: 3000
B21: Alejandro Rodriguez | C21: 20000 | G21: LAR | H21: 2800
B22: Honorarios contador | C22: =(C21+C34+2000+5000)*0.045 -> 1575
B23: Cristian Ramirez | H23: =SUM(H15:H22) -> 18750
B24: Edgar Joel Vega Martínez (Emplaye)
B25: ETIQUETAS CODICE
B26: CAJA RUTH GDL | D26: =3500*12 -> 42000
B27: GUAYABAS LA ESPERANZA | K27: =32*25 -> 800
B28: SANICHEM | K28: =4000/K27 -> 5
B29: IMSS | D29: 45000
B30: ADEUDO GALU | D30: 47000 | G30: =1600/15 -> 106.66667
B31: BOLSA 30 LBS CHAVINDA | C31: =1450*5 -> 7250 | G31: =G30/30 -> 3.5555556
B32: CAJA CARTON (PATAGONIA) 20 y 30 lbs | C32: =16.9*1.16*500 -> 9802
B33: AVV MONARCA | D33: 15000
B34: VERIFICACION FLOSOL | C34: 8000
C36: =SUM(C7:C34) -> 205337.82 | D36: =SUM(D7:D35) -> 376773.8
C39: 112000
C40: =D8+D9+C12+C26 -> 69999.8

Sheet 23 28 Feb
B1: GASTOS DE LA SEMANA | P1: RESUMEN — Feb 26
P2: Pagado | Q2: =C37 -> 206967.6
P3: Pendiente | Q3: =D37 -> 103500
P4: Ingresos | Q4: =I11 -> 227100
B5: CONCEPTO | C5: PAGO | D5: PENDIENTE | P5: Egresos | Q5: 0
B6: Semana del 23 al 28 Feb | C6: PAGO | E6: PENDIENTE | H6: ENTRADAS | P6: Balance (Ing−Pag−Eg) | Q6: =Q4-Q5-Q2 -> 20132.4
B7: NOMINA FV | C7: 100000 | H7: Proberry Crumble
B8: NOMINA CXM | C8: =I23 -> 21800 | H8: Proberry Bloque Fram | I8: 39100
B9: RAISA | C9: 30000 | D9: =C9 -> 30000 | H9: Proberry 80/20 | I9: 188000
B10: RAISA
B11: EMBAPACK | I11: =SUM(I7:I10) -> 227100
B12: ALEX Y RAFA | C12: 10000 | D12: =C12 -> 10000 | H12: Diferencia | I12: =I11-C37-E37 -> 20132.4
B13: CIPSA | M13: =9*60*13.6 -> 7344
B14: DEPACHO GARNICA | H14: OTROS GASTOS | M14: =M13/150 -> 48.96
B15: LORE (Transporte Personal) | F15: 8526 | H15: Soco | I15: 4000
B16: SIMA (CALIBRACION) | H16: TATA | I16: 4500
B17: ROBERTO REYES | H17: GUSTAVO | I17: 3500 | N17: del pago
B18: SINDULFO | F18: 49247.8 | H18: GUSTAVO gastos
B19: LALO AGUIRRE | C19: 10000 | H19: VERO | I19: 1950
B20: CIELO (TARIMAS) | H20: FRANCISCO (Cancun) | I20: 1850
B21: Alejandro Rodriguez | H21: AVV | I21: 3000
B22: Honorarios contador | C22: =(C7+C8)*0.042 -> 5115.6 | H22: LAR | I22: 3000
B23: Cristian Ramirez | I23: =SUM(I15:I22) -> 21800
B24: Edgar Joel Vega Martínez (Emplaye)
B25: ETIQUETAS CODICE
B26: CAJA RUTH GDL | D26: 42000
B27: GUAYABAS LA ESPERANZA | L27: =32*25 -> 800
B28: SANICHEM | L28: =4000/L27 -> 5
B29: IMSS | D29: 15000 | F29: 30000
B30: ADEUDO GALU | F30: =47000-E30 -> 47000 | H30: =1600/15 -> 106.66667
B31: BOLSA 30 LBS CHAVINDA | C31: =1450*5 -> 7250 | H31: =H30/30 -> 3.5555556
B32: CAJA CARTON (PATAGONIA) 20 y 30 lbs | C32: =16.9*1.16*500 -> 9802
B33: AVV MONARCA | F33: 15000
B34: VERIFICACION FLOSOL
B35: LAR | C35: 6500
B36: AVV | C36: 6500 | D36: =C36 -> 6500
C37: =SUM(C7:C36) -> 206967.6 | D37: =SUM(D7:D36) -> 103500 | F37: =SUM(F7:F34) -> 149773.8
C40: 112000
C41: =E8+E9+C12+C26 -> 10000

Sheet 02 07 Mar
B1: GASTOS DE LA SEMANA | P1: RESUMEN — Mar 26
P2: Pagado | Q2: =C36 -> 215104.2
P3: Pendiente | Q3: =D36 -> 244546.17
P4: Ingresos | Q4: =I11 -> 328790
B5: CONCEPTO | C5: PAGO | D5: PENDIENTE | P5: Egresos | Q5: 0
B6: Semana del 02 al 07 Marzo | C6: PAGO | D6: PENDIENTE | H6: ENTRADAS | P6: Balance (Ing−Pag−Eg) | Q6: =Q4-Q5-Q2 -> 113685.8
B7: NOMINA FV | C7: 110000 | D7: 70000 | H7: Proberry 80/20 | I7: 199760
B8: NOMINA CXM | C8: =I23 -> 19950 | H8: Proberry Crumble | I8: =258060/2 -> 129030
B9: RAISA | C9: 30000 | D9: 45000 | H9: Proberry Zarza
B10: RAISA
B11: EMBAPACK Bolsa Verde) | D11: =7467.5+1493.5 -> 8961 | I11: =SUM(I7:I10) -> 328790
B12: ALEX Y RAFA | D12: 10000 | H12: Diferencia | I12: =I11-C36-D36 -> -130860.37
B13: CIPSA | M13: =9*60*13.6 -> 7344
B14: DEPACHO GARNICA | M14: =M13/150 -> 48.96
B15: LORE (Transporte Personal) | F15: 8526 | H15: Soco | I15: 4000
B16: SIMA (CALIBRACION) | H16: TATA | I16: 4000 | J16: Pendiente Domingo
B17: ROBERTO REYES | H17: GUSTAVO | I17: 3000 | N17: del pago
B18: SINDULFO | F18: 49247.8 | H18: GUSTAVO gastos
B19: LALO AGUIRRE | C19: =2262+4549.7 -> 6811.7 | H19: VERO | I19: 1950
B20: CIELO (TARIMAS) | H20: FRANCISCO (Cancun) | I20: 1400
B21: Alejandro Rodriguez | H21: AVV | I21: 2800
B22: Honorarios contador | C22: =(C7+C8)*0.042 -> 5457.9 | D22: =(D7+D8)*0.042 -> 2940 | H22: LAR | I22: 2800
B23: Cristian Ramirez | D23: 28500 | I23: =SUM(I15:I22) -> 19950
B24: Edgar Joel Vega Martínez (Emplaye)
B25: ETIQUETAS CODICE
B26: CAJA RUTH GDL | C26: 20000 | D26: 28477.37
B27: GUAYABAS LA ESPERANZA | L27: =32*25 -> 800
B28: SANICHEM | L28: =4000/L27 -> 5
B29: IMSS | D29: 25000 | F29: 30000
B30: ADEUDO GALU | F30: =47000-D30 -> 47000 | H30: =1600/15 -> 106.66667
B31: BOLSA 30 LBS CHAVINDA | D31: 7250 | H31: =H30/30 -> 3.5555556
B32: CAJA CARTON (PATAGONIA) 20 y 30 lbs | C32: 1896.6 | D32: 15549.8
B33: FRENOS CAMIONETA JESUS | C33: 8120
B34: LAR | C34: 10000
B35: ETIQUETAS | C35: 2868 | D35: 2868
C36: =SUM(C7:C35) -> 215104.2 | D36: =SUM(D7:D35) -> 244546.17 | F36: =SUM(F7:F33) -> 134773.8

Sheet 09-14 Mar
B1: GASTOS DE LA SEMANA | P1: RESUMEN — Mar 26
P2: Pagado | Q2: =C37 -> 197583.92
P3: Pendiente | Q3: =D37 -> 122064.87
P4: Ingresos | Q4: =I11 -> 328790
B5: CONCEPTO | C5: PAGO | D5: PENDIENTE | P5: Egresos | Q5: =I23 -> 22000
B6: Semana del 09 al 14 de Marzo | C6: PAGO | D6: PENDIENTE | H6: ENTRADAS | P6: Balance (Ing−Pag−Eg) | Q6: =Q4-Q5-Q2 -> 109206.08
B7: NOMINA FV | C7: 110000 | H7: Proberry 80/20 | I7: 199760
B8: NOMINA CXM | C8: =I23 -> 22000 | H8: Proberry Crumble | I8: =258060/2 -> 129030
B9: RAISA | C9: 24415.44 | H9: Proberry Zarza
B10: RAISA | L10: CÁLCULOS
B11: EMBAPACK Bolsa Verde) | C11: 1493.5 | D11: 7467.5 | I11: =SUM(I7:I10) -> 328790 | L11: 39624 | M11: 38000
B12: ALEX Y RAFA | D12: 10000 | H12: Diferencia | I12: =I11-C37-D37 -> 9141.206 | L12: 33384 | M12: 32000
B13: CIPSA | L13: 104208 | M13: 100000
B14: DEPACHO GARNICA | L14: =SUM(L10:L13) -> 177216 | M14: =SUM(M11:M13) -> 170000
B15: LORE (Transporte Personal) | F15: 8526 | H15: Gastos LAR
B16: SIMA (CALIBRACION) | H16: TATA | I16: 4500 | M16: =L14-M14 -> 7216
B17: ROBERTO REYES | H17: GUSTAVO | I17: 3000 | N17: del pago
B18: SINDULFO | F18: 49247.8 | H18: GUSTAVO gastos | I18: 1750
B19: LALO AGUIRRE | H19: VERO | I19: 1950
B20: CIELO (TARIMAS) | H20: FRANCISCO (Cancun) | I20: 2800
B21: Alejandro Rodriguez | H21: AVV | I21: 4000
B22: Honorarios contador | C22: =(C7+C8+C33+C34)*0.042 -> 6822.984 | D22: =(D7+D8)*0.042 -> 0 | H22: LAR | I22: 4000
B23: Cristian Ramirez | D23: 28500 | I23: =SUM(I15:I22) -> 22000
B24: Edgar Joel Vega Martínez (Emplaye)
B25: JOSE HDEZ GARCIA (PAGO TARIMA) | D25: 15370
B26: CAJA RUTH GDL | D26: 28477.37
B27: GUAYABAS LA ESPERANZA | L27: =32*25 -> 800
B28: SANICHEM | L28: =4000/L27 -> 5
B29: IMSS | D29: 25000 | F29: 30000
B30: ADEUDO GALU | F30: =47000-D30 -> 47000 | H30: =1600/15 -> 106.66667
B31: BOLSA 30 LBS CHAVINDA | D31: =1450*5 -> 7250 | H31: =H30/30 -> 3.5555556
B32: CAJA CARTON (PATAGONIA) 20 y 30 lbs
B33: ALEJANDRO RODRIGUEZ | C33: 20000
B34: LAR | C34: 10452
B35: AVV | E35: =C35 -> 0
B36: MARACUYA | C36: 2400
C37: =SUM(C7:C36) -> 197583.92 | D37: =SUM(D7:D36) -> 122064.87 | E37: =SUM(E7:E35) -> 0 | F37: =SUM(F7:F33) -> 134773.8
B39: OTROS GASTOS
B40: ALEJANDRO RODRIGUEZ | C40: 20000
B41: LAR | C41: 18000
B42: Cristian Ramirez | C42: 28500
C43: =SUM(C40:C42) -> 66500

Sheet 16 21 Mar
B1: GASTOS DE LA SEMANA | P1: RESUMEN — Mar 26
P2: Pagado | Q2: =C36 -> 66360.1
P3: Pendiente | Q3: =D36 -> 266109.9
P4: Ingresos | Q4: =I11 -> 328790
B5: CONCEPTO | C5: PAGO | D5: PENDIENTE | P5: Egresos | Q5: =I25 -> 18950
B6: Semana del 16 al 21 Marzo | C6: PAGO | D6: PENDIENTE | H6: ENTRADAS | P6: Balance (Ing−Pag−Eg) | Q6: =Q4-Q5-Q2 -> 243479.9
B7: NOMINA FV | C7: 10000 | D7: =110000-C7 -> 100000 | H7: Proberry 80/20 | I7: 199760 | M7: PEDIENTE JESUS ALVAREZ TRANSPORTE ZACAPU
B8: NOMINA JACONA | C8: =3900+6900 -> 10800 | D8: =3900+6900 -> 10800 | H8: Proberry Crumble | I8: =258060/2 -> 129030
B9: NOMINA CXM | C9: 10000 | D9: =I25-C9 -> 8950 | H9: Proberry Zarza | M9: GASTOS PENDIENTE | N9: 5000
B10: RAISA | D10: 35000 | M10: FRENOS | N10: 8120
B11: RAISA | I11: =SUM(I7:I10) -> 328790 | M11: GAS (Gustavo le puso) | N11: 1000
B12: EMBAPACK Bolsa Verde) | D12: 7467.5 | H12: Diferencia | I12: =I11-C36-D36 -> -3680 | M12: GAS Efectivo Inge | N12: 500
B13: ALEX Y RAFA | D13: 10000 | L13: 46099 | M13: GAS Efectivo Inge | N13: 1000
B14: CIPSA | C14: 3828 | L14: 46100 | M14: REP CAMIONETA Efectivo Inge | N14: 1500
B15: DEPACHO GARNICA | H15: Gastos LAR | L15: 46100 | M15: REP CAMIONETA Efectivo Inge | N15: 1000
B16: LORE (Transporte Personal) | F16: 8526 | H16: TATA | I16: 4000 | L16: 46101 | M16: REP CAMIONETA Deposito | N16: 1000
B17: TRAMITES CFE | C17: =9000+4500+1000 -> 14500 | H17: GUSTAVO | I17: 3500 | N17: =SUM(N9:N16) -> 19120
B18: ROBERTO REYES | H18: GUSTAVO gastos | I18: 1500
B19: SINDULFO | F19: 49247.8 | H19: VERO | I19: 1950
B20: LALO AGUIRRE | H20: AVV | I20: 4000
B21: CIELO (TARIMAS) | H21: LAR | I21: 4000
B22: Honorarios contador | C22: =(C7+C8+C9+D7+D8+D9)*0.042 -> 6323.1
B23: Edgar Joel Vega Martínez (Emplaye) | C23: 3410
B24: JOSE HDEZ GARCIA (PAGO TARIMA)
B25: CAJA RUTH GDL | D25: 61642.4 | I25: =SUM(I15:I24) -> 18950
B26: GUAYABAS LA ESPERANZA
B27: SANICHEM
B28: IMSS | D28: 25000
B29: ADEUDO GALU
B30: BOLSA 30 LBS CHAVINDA | D30: =1450*5 -> 7250 | F30: 30000 | H30: =1600/15 -> 106.66667
B31: CAJA CARTON (PATAGONIA) 20 y 30 lbs | F31: =47000-D29 -> 47000 | H31: =H30/30 -> 3.5555556
B32: ALEJANDRO RODRIGUEZ | F32: 20000
B33: LAR
B34: AVV | E34: =C34 -> 0
B35: COMPRA LAPTOP | C35: 7499
C36: =SUM(C7:C35) -> 66360.1 | D36: =SUM(D7:D35) -> 266109.9 | F36: =SUM(F7:F34) -> 154773.8
B38: OTROS GASTOS
B39: ALEJANDRO RODRIGUEZ | C39: 20000
B40: LAR | C40: 18000
B41: Cristian Ramirez | C41: 28500
C42: =SUM(C39:C41) -> 66500

Sheet 23 28 Mar
B1: GASTOS DE LA SEMANA | P1: RESUMEN — Mar 26
P2: Pagado | Q2: =C36 -> 203156.91
P3: Pendiente | Q3: =D36 -> 113892.4
P4: Ingresos | Q4: =I11 -> 203456
B5: CONCEPTO | C5: PAGO | D5: PENDIENTE | P5: Egresos | Q5: =I25 -> 16950
B6: Semana del 23 al 28 Marzo | C6: PAGO | D6: PENDIENTE | H6: ENTRADAS | P6: Balance (Ing−Pag−Eg) | Q6: =Q4-Q5-Q2 -> -16650.91
B7: NOMINA FV | C7: 100000 | H7: Proberry 80/20 | J7: 33079 | M7: PEDIENTE JESUS ALVAREZ TRANSPORTE ZACAPU
B8: NOMINA JACONA | C8: =3900+6900 -> 10800 | H8: Proberry Crumble | I8: 203456
B9: NOMINA CXM | C9: =I25 -> 16950 | H9: Proberry Zarza | M9: GASTOS PENDIENTE | N9: 5000
B10: RAISA | M10: FRENOS | N10: 8120
B11: RAISA | I11: =SUM(I7:I10) -> 203456 | M11: GAS (Gustavo le puso) | N11: 1000
B12: EMBAPACK Bolsa Verde) | H12: Diferencia | I12: =I11-C36 -> 299.09 | M12: GAS Efectivo Inge | N12: 500
B13: ALEX Y RAFA | C13: 10000 | L13: 46099 | M13: GAS Efectivo Inge | N13: 1000
B14: CIPSA | L14: 46100 | M14: REP CAMIONETA Efectivo Inge | N14: 1500
B15: DEPACHO GARNICA | H15: Gastos LAR | L15: 46100 | M15: REP CAMIONETA Efectivo Inge | N15: 1000
B16: LORE (Transporte Personal) | F16: 8526 | H16: TATA | I16: 4000 | L16: 46101 | M16: REP CAMIONETA Deposito | N16: 1000
B17: PAGO BOTELLA PLASTICO 1 LTO | C17: 2501.41 | H17: GUSTAVO | I17: 4000 | N17: =SUM(N9:N16) -> 19120
B18: ROBERTO REYES | H18: GUSTAVO gastos | I18: 1000
B19: SINDULFO | F19: 49247.8 | H19: VERO | I19: 1950
B20: LALO AGUIRRE | H20: AVV | I20: 3000
B21: CIELO (TARIMAS) | H21: LAR | I21: 3000
B22: Honorarios contador | C22: =(C7+C8+C9+D7+D8+D9)*0.042 -> 5365.5
B23: Edgar Joel Vega Martínez (Emplaye)
B24: JOSE HDEZ GARCIA (PAGO TARIMA)
B25: CAJA RUTH GDL | D25: =57002.4+4640 -> 61642.4 | I25: =SUM(I15:I24) -> 16950 | L25: =17+5+13 -> 35
B26: GUAYABAS LA ESPERANZA | L26: 57
B27: SANICHEM | L27: =SUM(L25:L26) -> 92
B28: IMSS | D28: 25000
B29: ADEUDO GALU
B30: BOLSA 30 LBS CHAVINDA | D30: =1450*5 -> 7250 | F30: 30000 | H30: =1600/15 -> 106.66667
B31: CAJA CARTON (PATAGONIA) 20 y 30 lbs | F31: =47000-D29 -> 47000 | H31: =H30/30 -> 3.5555556
B32: ALEJANDRO RODRIGUEZ | D32: 20000
B33: LAR
B34: AVV (MONARCA) | C34: 50000
B35: ROCIO IMPI | C35: 7540
C36: =SUM(C7:C35) -> 203156.91 | D36: =SUM(D7:D35) -> 113892.4 | F36: =SUM(F7:F34) -> 134773.8

Sheet 30 Mar 04 Abril
B1: GASTOS DE LA SEMANA | P1: RESUMEN — Mar 26
P2: Pagado | Q2: =C36 -> 148113.9
P3: Pendiente | Q3: =D36 -> 153892.4
P4: Ingresos | Q4: =I11 -> 132880
B5: CONCEPTO | C5: PAGO | D5: PENDIENTE | P5: Egresos | Q5: =I23 -> 17950
B6: Semana del 30 de Marzo al 04 Abril | C6: PAGO | D6: PENDIENTE | H6: ENTRADAS | P6: Balance (Ing−Pag−Eg) | Q6: =Q4-Q5-Q2 -> -33183.9
B7: NOMINA FV | C7: 105000 | H7: Proberry 80/20 | I7: =199760/2 -> 99880 | J7: 33079 | M7: PEDIENTE JESUS ALVAREZ TRANSPORTE ZACAPU
B8: NOMINA JACONA | H8: Proberry Crumble
B9: NOMINA CXM | C9: =I23 -> 17950 | H9: Proberry Zarza | I9: 33000 | M9: GASTOS PENDIENTE | N9: 5000
B10: RAISA | M10: FRENOS | N10: 8120
B11: RAISA | I11: =SUM(I7:I10) -> 132880 | M11: GAS (Gustavo le puso) | N11: 1000
B12: EMBAPACK Bolsa Verde) | H12: Diferencia | I12: =I11-C36 -> -15233.9 | M12: GAS Efectivo Inge | N12: 500
B13: ALEX Y RAFA | D13: 10000 | L13: 46099 | M13: GAS Efectivo Inge | N13: 1000
B14: CIPSA | L14: 46100 | M14: REP CAMIONETA Efectivo Inge | N14: 1500
B15: DEPACHO GARNICA | H15: Gastos LAR | L15: 46100 | M15: REP CAMIONETA Efectivo Inge | N15: 1000
B16: LORE (Transporte Personal) | F16: 8526 | H16: TATA | I16: 4000 | L16: 46101 | M16: REP CAMIONETA Deposito | N16: 1000
B17: PAGO BOTELLA PLASTICO 1 LTO | H17: GUSTAVO | I17: 3000 | N17: =SUM(N9:N16) -> 19120
B18: ROBERTO REYES | H18: GUSTAVO gastos | I18: 1000
B19: SINDULFO | F19: 49247.8 | H19: VERO | I19: 1950
B20: LALO AGUIRRE | H20: AVV | I20: 4000
B21: CIELO (TARIMAS) | H21: LAR | I21: 4000
B22: Honorarios contador | C22: =(C7+C8+C9+D7+D8+D9)*0.042 -> 5163.9
B23: Edgar Joel Vega Martínez (Emplaye) | I23: =SUM(I15:I22) -> 17950
B24: JOSE HDEZ GARCIA (PAGO TARIMA)
B25: CAJA RUTH GDL | D25: =57002.4+4640 -> 61642.4 | L25: =17+5+13 -> 35
B26: GUAYABAS LA ESPERANZA | L26: 57
B27: SANICHEM | L27: =SUM(L25:L26) -> 92
B28: IMSS | D28: 25000
B29: ADEUDO GALU
B30: BOLSA 30 LBS CHAVINDA | D30: =1450*5 -> 7250 | F30: 30000 | H30: =1600/15 -> 106.66667
B31: CAJA CARTON (PATAGONIA) 20 y 30 lbs | F31: =47000-D29 -> 47000 | H31: =H30/30 -> 3.5555556
B32: ALEJANDRO RODRIGUEZ | C32: 20000
B33: LAR
B34: AVV (MONARCA) | D34: 50000
C36: =SUM(C7:C35) -> 148113.9 | D36: =SUM(D7:D35) -> 153892.4 | F36: =SUM(F7:F34) -> 134773.8

Sheet 06 11 Abril
B1: GASTOS DE LA SEMANA | P1: RESUMEN — Abr 26
P2: Pagado | Q2: =C35 -> 132365.92
P3: Pendiente | Q3: =D35 -> 153892.4
P4: Ingresos | Q4: =I11 -> 199760
B5: CONCEPTO | C5: PAGO | D5: PENDIENTE | P5: Egresos | Q5: =I23 -> 21950
B6: Semana del 06 al 11 Abril | C6: PAGO | D6: PENDIENTE | H6: ENTRADAS | P6: Balance (Ing−Pag−Eg) | Q6: =Q4-Q5-Q2 -> 45444.08
B7: NOMINA FV | C7: 78000 | H7: Proberry 80/20 | I7: =199760 -> 199760 | J7: 33079 | M7: PEDIENTE JESUS ALVAREZ TRANSPORTE ZACAPU
B8: NOMINA JACONA | C8: 12000 | H8: Proberry Crumble
B9: NOMINA CXM | C9: =I23 -> 21950 | H9: Proberry Zarza | M9: GASTOS PENDIENTE | N9: 5000
B10: RAISA | M10: FRENOS | N10: 8120
B11: RAISA | I11: =SUM(I7:I10) -> 199760 | M11: GAS (Gustavo le puso) | N11: 1000
B12: EMBAPACK Bolsa Verde) | H12: Diferencia | I12: =I11-C35 -> 67394.08 | M12: GAS Efectivo Inge | N12: 500
B13: ALEX Y RAFA | D13: 10000 | L13: 46099 | M13: GAS Efectivo Inge | N13: 1000
B14: CIPSA | C14: 2784 | L14: 46100 | M14: REP CAMIONETA Efectivo Inge | N14: 1500
B15: DEPACHO GARNICA | H15: Gastos LAR | L15: 46100 | M15: REP CAMIONETA Efectivo Inge | N15: 1000
B16: LORE (Transporte Personal) | F16: 8526 | H16: TATA | I16: 4000 | L16: 46101 | M16: REP CAMIONETA Deposito | N16: 1000
B17: CIRAM | C17: 3795.02 | H17: GUSTAVO | I17: 3000 | N17: =SUM(N9:N16) -> 19120
B18: ROBERTO REYES | H18: ALBAÑILES JOAQUIN | I18: 6000
B19: SINDULFO | F19: 49247.8 | H19: VERO | I19: 1950
B20: LALO AGUIRRE | H20: AVV | I20: 3500
B21: CIELO (TARIMAS) | H21: LAR | I21: 3500
B22: Honorarios contador | C22: =(C7+C8+C9+D7+D8+D9)*0.042 -> 4701.9
B23: Edgar Joel Vega Martínez (Emplaye) | I23: =SUM(I15:I22) -> 21950
B24: JOSE HDEZ GARCIA (PAGO TARIMA)
B25: CAJA RUTH GDL | D25: =57002.4+4640 -> 61642.4 | L25: =17+5+13 -> 35
B26: GUAYABAS LA ESPERANZA | L26: 57
B27: SANICHEM | L27: =SUM(L25:L26) -> 92
B28: IMSS | D28: 25000
B29: ADEUDO GALU
B30: BOLSA 30 LBS CHAVINDA | D30: =1450*5 -> 7250 | F30: 30000 | H30: =1600/15 -> 106.66667
B31: CAJA CARTON (PATAGONIA) 20 y 30 lbs | C31: 9135 | F31: =47000-D29 -> 47000 | H31: =H30/30 -> 3.5555556
B32: LAR
B33: AVV (MONARCA) | D33: 50000
C35: =SUM(C7:C34) -> 132365.92 | D35: =SUM(D7:D34) -> 153892.4 | F35: =SUM(F7:F33) -> 134773.8

Sheet 13 18 Abril
B1: GASTOS DE LA SEMANA | P1: RESUMEN — Abr 26
P2: Pagado | Q2: =C39 -> 210849.13
P3: Pendiente | Q3: =D39 -> 281703.18
P4: Ingresos | Q4: =I12 -> 323806.08
B5: CONCEPTO | C5: PAGO | D5: PENDIENTE | P5: Egresos | Q5: =I24 -> 20000
B6: Semana del 13 al 18 Abril | C6: PAGO | D6: PENDIENTE | H6: ENTRADAS | P6: Balance (Ing−Pag−Eg) | Q6: =Q4-Q5-Q2 -> 92956.95
B7: NOMINA FV | C7: 105000 | H7: Proberry 80/20 | J7: 33079 | M7: PEDIENTE JESUS ALVAREZ TRANSPORTE ZACAPU
B8: NOMINA JACONA | H8: Proberry Crumble | I8: 126412
B9: NOMINA CXM | C9: =I24 -> 20000 | H9: Proberry Zarza | M9: GASTOS PENDIENTE | N9: 5000
B10: RAISA | D10: 70000 | H10: Semana pasada | I10: ='06 11 Abril'!I12 -> 67394.08 | M10: FRENOS | N10: 8120
B11: RAISA | H11: Pafgo AVV | I11: 130000 | M11: GAS (Gustavo le puso) | N11: 1000
B12: EMBAPACK Bolsa Verde) | I12: =SUM(I7:I11) -> 323806.08 | M12: GAS Efectivo Inge | N12: 500
B13: ALEX Y RAFA | C13: 10000 | H13: Diferencia | I13: =I12-C39 -> 112956.95 | L13: 46099 | M13: GAS Efectivo Inge | N13: 1000
B14: CIPSA | D14: 2784 | L14: 46100 | M14: REP CAMIONETA Efectivo Inge | N14: 1500
B15: DEPACHO GARNICA | H15: Gastos LAR | L15: 46100 | M15: REP CAMIONETA Efectivo Inge | N15: 1000
B16: LORE (Transporte Personal) | D16: 6970 | F16: 8526 | H16: TATA | I16: 4000 | L16: 46101 | M16: REP CAMIONETA Deposito | N16: 1000
B17: CIRAM | D17: 3795.01 | H17: GUSTAVO | I17: 3000 | N17: =SUM(N9:N16) -> 19120
B18: ROBERTO REYES | H18: ALBAÑILES JOAQUIN | I18: 5800
B19: SINDULFO | F19: 49247.8 | H19: VERO | I19: 1950
B20: GLADYS (CERTIFICACION) | D20: 15000 | H20: AVV | I20: 3000
B21: DIKEN | D21: 1186.36 | H21: Tony | I21: 500
B22: CIELO ALEJANDRA (TARIMAS) GONZALO | D22: 32480 | H22: LAR | I22: 2750 | J22: 18250
B23: Honorarios contador | C23: =(C7+C8+C9+D7+D8+D9)*0.042 -> 5250 | I23: -1000 | J23: =J22-20000 -> -1750
B24: Edgar Joel Vega Martínez (Emplaye) | D24: 3970.21 | I24: =SUM(I15:I23) -> 20000
B25: JOSE HDEZ GARCIA (PAGO TARIMA) | D25: 15370 | L25: =17+5+13 -> 35
B26: JOSE HDEZ GARCIA (PAGO TARIMA) | D26: 15370 | I26: =I24+4000 -> 24000 | L26: 57
B27: CAJA RUTH GDLMK BOXES | C27: 30000 | D27: =57002.4+4640 -> 61642.4 | L27: =SUM(L25:L26) -> 92
B28: GUAYABAS LA ESPERANZA
B29: SANICHEM | D29: 4750.2
B30: IMSS FV | C30: 9676.45 | F30: 30000 | H30: =1600/15 -> 106.66667
B31: IMSS CXM | C31: 12652.68 | H31: =H30/30 -> 3.5555556
B32: ADEUDO GALU | F32: =47000-D32 -> 47000
B33: BOLSA 30 LBS CHAVINDA | D33: =1450*5 -> 7250
B34: CAJA CARTON (PATAGONIA) 20 y 30 lbs | C34: =15.75*1.16*1000 -> 18270 | D34: 9135
B35: LAR
B36: AVV (MONARCA)
B37: PAGO ACTA CONST FV PLUS
B38: CONVENIO IMSS CXM | D38: 32000
C39: =SUM(C7:C38) -> 210849.13 | D39: =SUM(D7:D38) -> 281703.18 | F39: =SUM(F7:F36) -> 134773.8
D42: =15*25 -> 375
D43: =D42*3 -> 1125
B45: NOTAS / PENDIENTES
B46: Malla Sombra 70%, 7.85 x 4.70 mts | C46: 2 pzas
B47: Malla Sombra 70%, 1.90 x 2.43 | C47: 2 pzas
B48: Malla Sombra 70%; 1.92 x 6.00 | C48: 2 pzas
B49: P. Malla Sombra 70%; 1.25 x 2.50 mts | C49: 2 pzas
B50: P. Malla Sombra 70%; 2.00 x 2.50 mts | C50: 1 pza
B51: P. Malla Sombra 70%; 2.50 x 2.50 mts | C51: 1 pza

Sheet 20 25 Abril
B1: GASTOS DE LA SEMANA | Q1: RESUMEN — Abr 26
Q2: Pagado | R2: =C44 -> 541297.31
Q3: Pendiente | R3: =D44 -> 55669.42
Q4: Ingresos | R4: =J12 -> 524873.2
B5: CONCEPTO | C5: PAGO | D5: PENDIENTE | Q5: Egresos | R5: =J24 -> 31050
B6: Semana del 20 al 25 Abril | C6: PAGO | D6: PENDIENTE | E6: PENDIENTE | I6: ENTRADAS | J6: 152000 | Q6: Balance (Ing−Pag−Eg) | R6: =R4-R5-R2 -> -47474.11
B7: NOMINA FV | C7: 110000 | I7: Proberry 80/20 | J7: 121000 | K7: 46137 | N7: PEDIENTE JESUS ALVAREZ TRANSPORTE ZACAPU
B8: NOMINA JACONA | I8: Proberry Crumble Maritimo 1/2 | J8: 126412 | K8: 46133
B9: NOMINA CXM | C9: =J24 -> 31050 | I9: MAURICIO CARO | J9: 126396.8 | K9: 46133 | N9: GASTOS PENDIENTE | O9: 5000
B10: RAISA | C10: 40426.65 | I10: MAURICIO CARO | J10: 151064.4 | K10: 46135 | N10: FRENOS | O10: 8120
B11: RAISA | I11: Semana Pasada | N11: GAS (Gustavo le puso) | O11: 1000
B12: EMBAPACK Bolsa Verde) | C12: =5379.5+1783.5+2551.12+3596 -> 13310.12 | J12: =SUM(J7:J11) -> 524873.2 | N12: GAS Efectivo Inge | O12: 500
B13: ALEX Y RAFA | D13: 10000 | I13: Diferencia | J13: =J12-C44 -> -16424.11 | M13: 46099 | N13: GAS Efectivo Inge | O13: 1000
B14: CIPSA | D14: 2784 | M14: 46100 | N14: REP CAMIONETA Efectivo Inge | O14: 1500
B15: DEPACHO GARNICA | I15: Gastos LAR | M15: 46100 | N15: REP CAMIONETA Efectivo Inge | O15: 1000
B16: LORE (Transporte Personal) | F16: 6970 | G16: 8526 | I16: TATA | J16: 4000 | M16: 46101 | N16: REP CAMIONETA Deposito | O16: 1000
B17: CIRAM | D17: 3795.01 | I17: GUSTAVO | J17: 3000 | O17: =SUM(O9:O16) -> 19120
B18: ROBERTO REYES | I18: ALBAÑILES JOAQUIN | J18: 5800
B19: SINDULFO | G19: 49247.8 | I19: JOAQUIN (PENDIENTE Y REVOLVEDORA) | J19: 2000
B20: GLADYS (CERTIFICACION) | D20: 15000 | I20: ALBERTO | J20: 2800
B21: DIKEN | C21: 1441.56 | I21: VERO | J21: 1950
B22: CIELO ALEJANDRA (TARIMAS) GONZALO | F22: 32480 | I22: AVV | J22: 3500
B23: Honorarios contador | C23: =(C7+C8+C9+E7+E8+E9+C40+C39)*0.042 -> 13727.7 | I23: JORGE ALFARO | J23: 8000
B24: Edgar Joel Vega Martínez (Emplaye) | D24: 3970.21 | J24: =SUM(J16:J23) -> 31050
B25: JOSE HDEZ GARCIA (PAGO TARIMA) | D25: 15370 | I25: LAR | J25: 3500 | M25: =17+5+13 -> 35
B26: JOSE HDEZ GARCIA (PAGO TARIMA) | F26: 15370 | J26: =J24+4000 -> 35050 | M26: 57
B27: CAJA RUTH GDLMK BOXES | C27: =57002.4+4640-30000 -> 31642.4 | M27: =SUM(M25:M26) -> 92
B28: GUAYABAS LA ESPERANZA
B29: SANICHEM | D29: 4750.2
B30: IMSS FV | G30: 30000 | I30: =1600/15 -> 106.66667
B31: IMSS CXM | C31: 20000 | I31: =I30/30 -> 3.5555556
B32: ADEUDO GALU | G32: =47000-E32 -> 47000
B33: BOLSA 30 LBS CHAVINDA | C33: 18000 | F33: =1450*5 -> 7250
B34: CAJA CARTON (PATAGONIA) 20 y 30 lbs | C34: 28739
B35: CAJA CARTON (PATAGONIA) 20 y 30 lbs | C35: =16.9*1.16*500 -> 9802
B36: LAR
B37: PRIMUS LAB | C37: 2277.13
B38: SAM JARABES TAPATIOS | C38: 3888 | I38: =6*60*4 -> 1440
B39: OMAR GUERRERO | C39: 85800
B40: OMAR GUERRERO | C40: 100000
B41: MATERIAL RAISA | C41: =2329+1790+330+5499.9+688.35+737.5+1050 -> 12424.75
B42: PONCHO MADRIGAL (Fresa) | C42: 18768
B43: PAGO ACTA CONST FV PLUS
C44: =SUM(C7:C43) -> 541297.31 | D44: =SUM(D7:D43) -> 55669.42 | G44: =SUM(G7:G39) -> 134773.8
D47: 750
D48: 2250
B50: NOTAS / PENDIENTES
B51: Malla Sombra 70%, 7.85 x 4.70 mts | C51: 2 pzas | I51: OTROS GASTOS
B52: Malla Sombra 70%, 1.90 x 2.43 | C52: 2 pzas | J52: 96000
B53: Malla Sombra 70%; 1.92 x 6.00 | C53: 2 pzas | J53: 30000
B54: P. Malla Sombra 70%; 1.25 x 2.50 mts | C54: 2 pzas | I54: Omar | J54: =-85800*1.04 -> -89232 | K54: 80000 | L54: =K54*1.045 -> 83600
B55: P. Malla Sombra 70%; 2.00 x 2.50 mts | C55: 1 pza | I55: IMSS | J55: -20000 | L55: 20000
B56: P. Malla Sombra 70%; 2.50 x 2.50 mts | C56: 1 pza | I56: Caja Patagonia | J56: =-16.9*1.16*500 -> -9802 | L56: 10000
J57: =SUM(J52:J56) -> 6966 | L57: =SUM(L54:L56) -> 113600
L58: =J52+J53-L57 -> 12400

Sheet 27 Abril 02 Mayo
B1: GASTOS DE LA SEMANA | N1: RESUMEN — Abr 26
N2: Pagado | O2: =C51 -> 330644.32
N3: Pendiente | O3: =D51 -> 52600.2
N4: Ingresos | O4: =I13 -> 333976
B5: CONCEPTO | C5: PAGO | D5: PENDIENTE | N5: Egresos | O5: =I24 -> 19750
B6: Semana del 27 Abril 02 Mayo | C6: PAGO | D6: PENDIENTE | H6: ENTRADAS | N6: Balance (Ing−Pag−Eg) | O6: =O4-O5-O2 -> -16418.32
B7: NOMINA FV | C7: 110000 | H7: Proberry 80/20 | I7: 121000 | J7: 46139
B8: NOMINA JACONA SABADO | C8: 10000 | H8: Proberry Crumble Aguascalientes | I8: 212976 | J8: 46142
B9: NOMINA JACONA MIERCOLES | C9: 15645
B10: NOMINA CXM | C10: =I24 -> 19750 | H10: Proberry Picos | J10: xx/04/2026
B11: Honorarios contador | C11: =(D7+D8+D10+C7+C8+C10+C9+D9)*0.042 -> 6526.59
B12: RAISA | H12: Semana Pasada
B13: EMBAPACK Bolsa Verde | C13: 10788 | I13: =SUM(I7:I12) -> 333976
B14: EMBAPACK Bolsa AZUL | C14: =3626+3596 -> 7222 | H14: Diferencia | I14: =I13-C51 -> 3331.68
B15: ALEX Y RAFA | C15: 10000
B16: CIPSA | C16: 2784
B17: DEPACHO GARNICA | C17: =4476.15*2 -> 8952.3 | H17: Gastos LAR
B18: LORE (Transporte Personal) | H18: TATA | I18: 4000
B19: CIRAM | C19: 3795.01 | H19: GUSTAVO | I19: 3000 | J19: Pendiente Festivo
B20: ROBERTO REYES | H20: ALBERTO | I20: 2800
B21: SINDULFO | F21: 49247.8 | H21: VERO | I21: 1950
B22: GLADYS (CERTIFICACION) | C22: 14500 | H22: AVV | I22: 3000
B23: DIKEN | H23: JORGE ALFARO | I23: 5000 | J23: 3000 | K23: A cuenta
B24: CIELO ALEJANDRA (TARIMAS) GONZALO | D24: 32480 | I24: =SUM(I18:I23) -> 19750
B26: Edgar Joel Vega Martínez (Emplaye) | C26: 3970.21
B27: JOSE HDEZ GARCIA (PAGO TARIMA) | C27: 15370 | H27: LAR | I27: 3500 | L27: =17+5+13 -> 35
B28: JOSE HDEZ GARCIA (PAGO TARIMA) | D28: 15370 | I28: =I24+4000 -> 23750 | L28: 57
B29: CAJA RUTH GDLMK BOXES | L29: =SUM(L27:L28) -> 92
B30: GUAYABAS LA ESPERANZA
B31: SANICHEM | D31: 4750.2
B32: IMSS FV | F32: 30000 | H32: =1600/15 -> 106.66667
B33: IMSS CXM | H33: =H32/30 -> 3.5555556
B34: ADEUDO GALU | F34: =47000 -> 47000
B35: BOLSA 30 LBS CHAVINDA
B36: CAJA CARTON (PATAGONIA) 20 y 30 lbs | C36: 9135
B37: CAJA CARTON (PATAGONIA) 20 y 30 lbs | C37: 11629
B38: CAJA CARTON (PATAGONIA) 20 y 30 lbs | C38: 9135
B39: LAR | C39: =14200+5400 -> 19600
B40: Varios (Llaves reparacion FV) | C40: 520
B41: PRIMUS LAB
B42: SAM JARABES TAPATIOS | H42: =6*60*4 -> 1440
B43: Aceros Gutz | C43: 1076
B44: FLEJE MONTERREY | C44: 600
B45: IMSS (DEPOSITO A CUENTA AVV) | C45: 10000
B46: Pintura FV ( cubeta Esmalte) | C46: 3310
B47: MATERIAL RAISA | C47: =7020+3000+1910+290 -> 12220
B48: TRES GUERRAS | C48: 2516.21
B49: PAGO ACTA CONST FV PLUS | C49: 11600 | D49: J. JESUS MAGAÑA TORRES, BBVA 0134654285
B50: IMPRENTA BERNARDO | C50: 2900
C51: =SUM(C7:C49) -> 330644.32 | D51: =SUM(D7:D50) -> 52600.2 | F51: =SUM(F7:F44) -> 126247.8
D55: =D54*3 -> 0
B57: NOTAS / PENDIENTES
B58: Malla Sombra 70%, 7.85 x 4.70 mts | C58: 2 pzas | H58: OTROS GASTOS
B59: Malla Sombra 70%, 1.90 x 2.43 | C59: 2 pzas | I59: 96000
B60: Malla Sombra 70%; 1.92 x 6.00 | C60: 2 pzas | I60: 30000
B61: P. Malla Sombra 70%; 1.25 x 2.50 mts | C61: 2 pzas | H61: Omar | I61: =-85800*1.04 -> -89232 | J61: 80000 | K61: =J61*1.045 -> 83600
B62: P. Malla Sombra 70%; 2.00 x 2.50 mts | C62: 1 pza | H62: IMSS | I62: -20000 | K62: 20000
B63: P. Malla Sombra 70%; 2.50 x 2.50 mts | C63: 1 pza | H63: Caja Patagonia | I63: =-16.9*1.16*500 -> -9802 | K63: 10000
I64: =SUM(I59:I63) -> 6966 | K64: =SUM(K61:K63) -> 113600
K65: =I59+I60-K64 -> 12400

Sheet 04 09 Mayo
B1: GASTOS DE LA SEMANA | M1: RESUMEN — May 26
M2: Pagado | N2: =C46 -> 180013.84
M3: Pendiente | N3: =D46 -> 112478.9
M4: Ingresos | N4: =I13 -> 193267.8
B5: CONCEPTO | C5: PAGO | D5: PENDIENTE | M5: Egresos | N5: =I25 -> 18850
B6: Semana del 04 al 09 Mayo | C6: PAGO | D6: PENDIENTE | H6: ENTRADAS | M6: Balance (Ing−Pag−Eg) | N6: =N4-N5-N2 -> -5596.04
B7: NOMINA FV | C7: 110000 | H7: Proberry 80/20 Julio caja 10 lbs | I7: 193267.8 | J7: 46150
B8: NOMINA JACONA SABADO | H8: Proberry Crumble Aguascalientes
B9: NOMINA JACONA MIERCOLES
B10: NOMINA CXM | C10: =I27 -> 21850
B11: Honorarios contador | C11: =(D7+D8+D10+C7+C8+C10+C9+D9)*0.042 -> 5537.7
B12: RAISA | H12: Semana Pasada
B13: Aceros Gutz | I13: =SUM(I7:I12) -> 193267.8
B14: ALEX Y RAFA | D14: 10000 | H14: Diferencia | I14: =I13-C46 -> 13253.96
B15: BOLSA 30 LBS CHAVINDA
B16: CIELO ALEJANDRA (TARIMAS) GONZALO | D16: 32480
B17: CIPSA | H17: Gastos LAR | K17: =2800/6 -> 466.66667
B18: CIRAM | H18: TATA | I18: 4000
B19: DEPACHO GARNICA | D19: =4476.15*2 -> 8952.3 | H19: GUSTAVO | I19: 3500
B20: DIKEN | H20: FRANCISCO CANCUN | I20: 500
B21: Edgar Joel Vega Martínez (Emplaye) | C21: 4235.94 | H21: ALBERTO CHALAN | I21: 900
B22: EMBAPACK Bolsa AZUL | H22: VERO | I22: 1950
B23: EMBAPACK Bolsa Verde) | H23: AVV | I23: 3000 | J23: 5000 | K23: Pendiente
B24: GALU | F24: =47000 -> 47000 | H24: JORGE ALFARO | I24: 5000
B25: GLADYS (CERTIFICACION) | I25: =SUM(I18:I24) -> 18850
B26: GUAYABAS LA ESPERANZA | H26: LAR | I26: =I23 -> 3000
B27: IMSS (DEPOSITO A CUENTA AVV) | I27: =I25+I26 -> 21850
B28: IMSS CXM | D28: 26453.74 | F28: 46170
B29: IMSS CXM | D29: 14592.86 | F29: 46201
B30: IMSS FV | H30: =60/6 -> 10 | I30: =45000 -> 45000 | J30: =I30/H30 -> 4500
B31: JOSE HDEZ GARCIA (PAGO TARIMA) | C31: 15370
B32: LAR
B33: LORE (Transporte Personal)
B34: MATERIAL RAISA
B35: MK BOXES RUTH GDL | D35: 20000
B36: PATAGONIA CAJA CARTON y 30 lbs | C36: =9135*2 -> 18270
B37: PATAGONIA CAJA CARTON y 30 lbs
B38: PATAGONIA CAJA CARTON y 30 lbs
B39: PRIMUS LAB | H39: =6*60*4 -> 1440 | J39: OTROS GASTOS
B40: ROBERTO REYES | J40: EDUARDO VACA TRANSPORTE
B41: SAM JARABES TAPATIOS | J41: 8 PERSONAS O MAS | K41: 1300
B42: SANICHEM | C42: 4750.2 | F42: 49247.8 | J42: 7 PERSONAS | K42: 1000
B43: SINDULFO | J43: 5 A 6 PERSONAS | K43: 800
J44: 4 PERSONAS | K44: 700
F45: =SUM(F7:F38) -> 139371
C46: =SUM(C7:C44) -> 180013.84 | D46: =SUM(D7:D45) -> 112478.9
D50: =D49*3 -> 0
D51: =997/1661 -> 0.60024082
B52: NOTAS / PENDIENTES
B53: Malla Sombra 70%, 7.85 x 4.70 mts | C53: 2 pzas
B54: Malla Sombra 70%, 1.90 x 2.43 | C54: 2 pzas
B55: Malla Sombra 70%; 1.92 x 6.00 | C55: 2 pzas | D55: =25*50 -> 1250 | H55: OTROS GASTOS
B56: P. Malla Sombra 70%; 1.25 x 2.50 mts | C56: 2 pzas | D56: =D55 -> 1250 | I56: 96000
B57: P. Malla Sombra 70%; 2.00 x 2.50 mts | C57: 1 pza | D57: =D55*5 -> 6250 | I57: 30000
B58: P. Malla Sombra 70%; 2.50 x 2.50 mts | C58: 1 pza | H58: Omar | I58: =-85800*1.04 -> -89232 | J58: 80000 | K58: =J58*1.045 -> 83600
H59: IMSS | I59: -20000 | K59: 20000
H60: Caja Patagonia | I60: =-16.9*1.16*500 -> -9802 | K60: 10000
I61: =SUM(I56:I60) -> 6966 | K61: =SUM(K58:K60) -> 113600
K62: =I56+I57-K61 -> 12400

Sheet 11 16 Mayo
B1: GASTOS DE LA SEMANA | M1: RESUMEN — May 26
M2: Pagado | N2: =C49 -> 365775.32
M3: Pendiente | N3: =D49 -> 311948.59
M4: Ingresos | N4: =H13 -> 353464
B5: CONCEPTO | C5: PAGO | D5: PENDIENTE | M5: Egresos | N5: =H26 -> 19450
B6: Semana del 11 al 16 Mayo | C6: PAGO | D6: PENDIENTE | G6: ENTRADAS | M6: Balance (Ing−Pag−Eg) | N6: =N4-N5-N2 -> -31761.318
B7: NOMINA FV | C7: =(63000-9000-5000-15000-4800-1000-7000)+88800 -> 110000 | G7: Proberry 80/20 Julio caja 20 lbs | H7: 199760 | I7: 46157
B8: NOMINA JACONA SABADO | C8: 9000 | G8: Proberry Crumble Aguascalientes | H8: 128704 | I8: 46155
B9: NOMINA JACONA MIERCOLES | G9: Pago Luinni | H9: 25000
B10: NOMINA CXM | C10: =H28 -> 24450
B11: Honorarios contador | C11: =(H8+H7)*0.042 -> 13795.488
B12: RAISA | C12: 7000 | G12: Semana Pasada
B13: RAISA | C13: 61302.86 | H13: =SUM(H7:H12) -> 353464
B14: Aceros Gutz | G14: Diferencia | H14: =H13-C49 -> -12311.318
B15: ALEX Y RAFA | C15: 10000 | D15: 10000
B16: BOLSA 30 LBS CHAVINDA
B17: CIELO ALEJANDRA (TARIMAS) GONZALO | D17: 32480 | G17: Gastos LAR
B18: CIPSA | D18: =3886 -> 3886 | G18: TATA | H18: 4000
B19: CIRAM | D19: 6050 | G19: GUSTAVO | H19: 3500
B20: CODICE ETIQUETAS | D20: 3596.65 | G20: FRANCISCO CANCUN | H20: =3500-400 -> 3100
B21: DEPACHO GARNICA | C21: =4476.15+4476.15 -> 8952.3 | G21: GASTOS | H21: 900
B22: DIKEN | D22: 2033 | G22: VERO | H22: 1950
B23: Edgar Joel Vega Martínez (Emplaye) | D23: 8129.69 | G23: AVV | I23: 5000
B24: EMBAPACK Bolsa AZUL | C24: 6666.98 | G24: JORGE ALFARO | H24: 5000
B25: EMBAPACK Bolsa Verde) | G25: ARTURO "PIÑA" | H25: 1000
B26: EDUARDO AGUIRRE | C26: 7508.23 | H26: =SUM(H18:H25) -> 19450
B27: GALU | D27: 47000 | G27: LAR | H27: =H24 -> 5000
B28: GLADYS (CERTIFICACION) | H28: =H26+H27 -> 24450 | I28: =SUM(I18:I27) -> 5000 | J28: =SUM(H28:I28) -> 29450
B29: GUAYABAS LA ESPERANZA
B30: IMSS (DEPOSITO A CUENTA AVV)
B31: IMSS CXM | D31: 26453.74 | I31: 12800 | J31: Factura | K31: =120000 -> 120000
B32: IMSS CXM | D32: 14592.86 | H32: LAR DEBITO | I32: 12800 | J32: Factura | K32: =H26+I28+H27 -> 29450
B33: IMSS FV | C33: 14685.06 | H33: OZ | I33: 50000 | K33: =SUM(K31:K32) -> 149450
B34: JOSE HDEZ GARCIA (PAGO TARIMA) | D34: 30740 | H34: EFECTIVO | I34: 18500
B35: LAR | C35: =5000+4800 -> 9800 | H35: MONA | I35: 30000
B36: LORE (Transporte Personal) | H36: AVV | I36: =I23 -> 5000
B37: MATERIAL RAISA | H37: GUSTAVO | I37: 19450 | J37: Factura
B38: MK BOXES RUTH GDL | D38: 77738.85 | H38: LAR DEBITO F | I38: 12800 | J38: Factura
B39: PATAGONIA CAJA CARTON y 30 lbs | C39: 56045.4 | I39: =SUM(I32:I38) -> 148550 | K39: =I39-K33 -> -900
B40: PATAGONIA CAJA CARTON y 30 lbs | C40: 9802 | I40: OTROS GASTOS
B41: PATAGONIA CAJA CARTON y 30 lbs | I41: EDUARDO VACA TRANSPORTE
B42: PRIMUS LAB | I42: 8 PERSONAS O MAS | J42: 1300
B43: ROBERTO REYES | I43: 7 PERSONAS | J43: 1000
B44: SAM JARABES TAPATIOS | I44: 5 A 6 PERSONAS | J44: 800
B45: SANICHEM | C45: 1292 | I45: 4 PERSONAS | J45: 700
B46: SINDULFO | D46: 49247.8
B47: BATAS, DIESEL, HOMEDEPOT | C47: =1000+500+964+2210 -> 4674
B48: IMPUESTOS LAR FEBRERO | C48: 10801
C49: =SUM(C7:C48) -> 365775.32 | D49: =SUM(D7:D48) -> 311948.59
D53: =D52*3 -> 0
D54: =997/1661 -> 0.60024082
B55: NOTAS / PENDIENTES | G55: OTROS GASTOS
B56: Malla Sombra 70%, 7.85 x 4.70 mts | C56: 2 pzas | H56: 96000
B57: Malla Sombra 70%, 1.90 x 2.43 | C57: 2 pzas | H57: 30000
B58: Malla Sombra 70%; 1.92 x 6.00 | C58: 2 pzas | D58: =25*50 -> 1250 | G58: Omar | H58: =-85800*1.04 -> -89232 | I58: 80000 | J58: =I58*1.045 -> 83600
B59: P. Malla Sombra 70%; 1.25 x 2.50 mts | C59: 2 pzas | D59: =D58 -> 1250 | G59: IMSS | H59: -20000 | J59: 20000
B60: P. Malla Sombra 70%; 2.00 x 2.50 mts | C60: 1 pza | D60: =D58*5 -> 6250 | G60: Caja Patagonia | H60: =-16.9*1.16*500 -> -9802 | J60: 10000
B61: P. Malla Sombra 70%; 2.50 x 2.50 mts | C61: 1 pza | H61: =SUM(H56:H60) -> 6966 | J61: =SUM(J58:J60) -> 113600
J62: =H56+H57-J61 -> 12400

Sheet 18 23 Mayo
B1: GASTOS DE LA SEMANA | O1: RESUMEN — May 26
O2: Pagado | P2: =C51 -> 186422.02
O3: Pendiente | P3: =D51 -> 331571.09
O4: Ingresos | P4: =I13 -> 206448
B5: CONCEPTO | C5: PAGO | D5: PENDIENTE | O5: Egresos | P5: =I26 -> 23500
B6: Semana del 18 AL 23 Mayo | C6: PAGO | D6: PENDIENTE | H6: ENTRADAS | O6: Balance (Ing−Pag−Eg) | P6: =P4-P5-P2 -> -3474.016
B7: NOMINA FV | C7: 110000 | D7: =110000-C7 -> 0 | H7: Proberry 80/20 Julio caja 10 lbs
B8: NOMINA JACONA Y OCUMICHO SABADO | C8: 10000 | H8: Crumble Luis Glez | I8: 206448 | J8: 46164 | K8: =I8*0.042 -> 8670.816 | L8: =I8-K8 -> 197777.18
B9: NOMINA JACONA Y OCUMICHO MIERCOLES | D9: 20000 | H9: Cubeta Crumble Aguscalientes
B10: NOMINA CXM | C10: =I28 -> 27000 | H10: Picos Fruta
B11: Honorarios contador | C11: =(I8+I7+I10+I11)*0.042 -> 8670.816 | H11: Zarzamora
B12: RAISA EFECTIVO
B13: RAISA | I13: =SUM(I7:I12) -> 206448
B14: Aceros Gutz | H14: Diferencia | I14: =I13-C51 -> 20025.984
B15: ALEX Y RAFA | D15: 10000
B16: BOLSA 30 LBS CHAVINDA | H16: Gastos LAR
B17: CIELO ALEJANDRA (TARIMAS) GONZALO | D17: 32480 | H17: TATA | I17: 4000
B18: CIPSA | D18: =3886 -> 3886 | H18: GUSTAVO | I18: 3000
B19: CIRAM | H19: GASTOS GUS | I19: =1500+300+50 -> 1850
B20: CHRISTIAN MANUEL (TAMINAS) | C20: 1044 | H20: FRANCISCO CANCUN | I20: 3400
B21: CODICE ETIQUETAS | D21: 3596.65 | H21: LUZ TALLER, Inter, Limpieza y copas
B22: DEPACHO GARNICA (Pago Febrero 2026) | D22: =4476.15+4476.15 -> 8952.3 | H22: VERO | I22: 1950
B23: DIKEN | D23: 2033 | H23: AVV | I23: 3500
B24: DIPAC BOLSA CHAVINDA | H24: RODOLFO | I24: 3500
A25: Dipac | B25: Edgar Joel Vega Martínez (Emplaye) | D25: 8129.69 | H25: AYUDANTE RODOLFO | I25: 2300
B26: EMBAPACK Bolsa TRNASPARENTE | C26: 7134 | I26: =SUM(I16:I25) -> 23500
B27: EMBAPACK Bolsa AZUL) | C27: =3596 -> 3596 | H27: LAR | I27: 3500
B28: EDUARDO AGUIRRE | I28: =I26+I27 -> 27000
B29: GALU | D29: 47000
B30: GLADYS (CERTIFICACION) | I30: LAR PAGOS | J30: 40000
B31: GUAYABAS LA ESPERANZA | I31: IMSS | J31: 26500 | K31: EFECTIVO | M31: 165000
B32: IMSS (DEPOSITO A CUENTA AVV) | M32: 25000
B33: IMSS CXM | D33: 52907.48 | F33: 46170 | I33: CONTADOR | J33: 50000 | K33: EFECTIVO | M33: =M31-M32 -> 140000
B34: IMSS CXM | D34: 14592.86 | F34: 46201 | I34: LAR DEBITO | J34: 12500 | K34: Factura
B35: IMSS FV | I35: OZ | J35: 42500 | K35: Factura
B36: JOSE HDEZ GARCIA (PAGO TARIMA) | D36: 30740 | I36: GUSTAVO | J36: 26500 | K36: Factura
B37: LAR seguro aveo | C37: 2729 | I37: GABY | J37: 12500 | K37: Factura
B38: LORE (Transporte Personal)
B39: MATERIAL RAISA | I39: OTROS GASTOS
B40: MK BOXES RUTH GDL | D40: 77738.85 | I40: NOMINA | J40: =SUM(J33:J39) -> 144000
B41: PATAGONIA CAJA CARTON y 30 lbs | C41: 14697.2 | J41: =J30+J31+J40 -> 210500 | K41: =197000-J41 -> -13500
B42: PATAGONIA CAJA CARTON y 30 lbs | H42: OTROS GASTOS
B43: PATAGONIA CAJA CARTON y 30 lbs | H43: CONSEGUIR FACTURA | I43: 12800 | J43: Factura
B44: PRIMUS LAB | D44: 6086.26 | I44: 12800 | J44: Factura
B45: ROBERTO REYES | I45: 19450 | J45: Factura
B46: SAM JARABES TAPATIOS | I46: 17800 | J46: Factura
B47: SANICHEM | I47: SINDULFO | L47: 49247.8
B48: STEREN NEBULIZADORES | C48: 1551
B49: BATAS, DIESEL, HOMEDEPOT | J49: OTROS GASTOS
B50: IMPUESTOS LAR | D50: 13428 | J50: EDUARDO VACA TRANSPORTE
C51: =SUM(C7:C50) -> 186422.02 | D51: =SUM(D7:D50) -> 331571.09 | J51: 8 PERSONAS O MAS | K51: 1300
J52: 7 PERSONAS | K52: 1000
B53: =D44+C24+C27+C50 -> 9682.26 | J53: 5 A 6 PERSONAS | K53: 800
J54: 4 PERSONAS | K54: 700
B57: NOTAS / PENDIENTES
B58: Malla Sombra 70%, 7.85 x 4.70 mts | C58: 2 pzas
B59: Malla Sombra 70%, 1.90 x 2.43 | C59: 2 pzas
B60: Malla Sombra 70%; 1.92 x 6.00 | C60: 2 pzas | D60: =25*50 -> 1250
B61: P. Malla Sombra 70%; 1.25 x 2.50 mts | C61: 2 pzas | D61: =D60 -> 1250
B62: P. Malla Sombra 70%; 2.00 x 2.50 mts | C62: 1 pza | D62: =D60*5 -> 6250
B63: P. Malla Sombra 70%; 2.50 x 2.50 mts | C63: 1 pza

Sheet 25 30 Mayo
B1: GASTOS DE LA SEMANA | Q1: RESUMEN — May 26
Q2: Pagado | R2: =C53 -> 314720.91
Q3: Pendiente | R3: =D53 -> 263589.84
Q4: Ingresos | R4: =J13 -> 311700
B5: CONCEPTO | C5: PAGO | D5: PENDIENTE | Q5: Egresos | R5: =J27 -> 20250
B6: Semana del 18 AL 23 Mayo | C6: PAGO | E6: PENDIENTE | I6: ENTRADAS | Q6: Balance (Ing−Pag−Eg) | R6: =R4-R5-R2 -> -23270.91
B7: NOMINA FV | C7: 110000 | I7: Proberry 80/20 Julio caja 10 lbs | J7: 184700 | K7: 46168 | L7: =J7-(J7*0.042) -> 176942.6
B8: NOMINA JACONA Y OCUMICHO SABADO | I8: Crumble Luis Glez
B9: NOMINA JACONA Y OCUMICHO MIERCOLES | I9: Cubeta Crumble Aguscalientes | J9: 127000 | K9: 46171
B10: NOMINA CXM | C10: =J29 -> 25000 | I10: Picos Fruta
B11: Honorarios contador | C11: =(J7+J8+J9+J10+J11+J12)*0.042 -> 13091.4 | I11: Zarzamora | K11: 68000 | L11: =SUM(K10:K11) -> 68000
B12: RAISA EFECTIVO
B13: RAISA | D13: 40000 | J13: =SUM(J7:J12) -> 311700
B14: Aceros Gutz | I14: Diferencia | J14: =J13-C53 -> -3020.91
B15: ALEX Y RAFA | C15: 10000
B16: BOLSA 30 LBS CHAVINDA | I16: Gastos LAR
B17: CIELO ALEJANDRA (TARIMAS) GONZALO | D17: 32480 | I17: TATA | J17: 4000 | K17: =J17 -> 4000
B18: CIPSA (Control de Plagas) | D18: =3886 -> 3886 | I18: GUSTAVO | J18: 3000 | K18: =J18 -> 3000
B19: CIRAM | I19: GASTOS GUS
B20: CODICE ETIQUETAS | C20: 4172.11 | I20: FRANCISCO CANCUN | J20: 1500 | K20: =J20 -> 1500
B21: DEPACHO GARNICA (Pago Febrero 2026) | D21: 8952.3 | I21: LUZ TALLER, Inter, Limpieza y copas
B22: DIKEN | D22: 2033 | I22: VERO | J22: 1950
B23: DIPAC BOLSA CHAVINDA | I23: RODOLFO | J23: 3500
A24: Dipac | B24: Edgar Joel Vega Martínez (Emplaye) | D24: 8129.69 | I24: AYUDANTE RODOLFO | J24: 2800 | K24: =J25 -> 3500
B25: EMBAPACK Bolsa AZUL y verde | C25: 1783 | I25: AVV | J25: 3500 | K25: =J26 -> 0
B26: EMBAPACK Bolsa AZUL) | C26: =3596 -> 3596 | K26: =SUM(K17:K25) -> 12000
B27: EDUARDO AGUIRRE | J27: =SUM(J16:J26) -> 20250
B28: GALU | D28: 60000 | F28: =47000 -> 47000 | I28: LAR | J28: 4750
B29: GLADYS (CERTIFICACION) | D29: 15000 | J29: =J27+J28 -> 25000
B30: GUAYABAS LA ESPERANZA
B31: IMSS (DEPOSITO A CUENTA AVV) | I31: =85000+50000 -> 135000 | N31: 165000
B32: IMSS CXM | C32: =14592.86+11860.88 -> 26453.74 | G32: 46170 | N32: 25000
B33: IMSS CXM | F33: =14592.86 -> 14592.86 | G33: 46201 | N33: =N31-N32 -> 140000
B34: IMSS FV
B35: JOSE HDEZ GARCIA (PAGO TARIMA) | C35: 15370 | D35: 15370
B36: JOSE "CARAS" EQUIPO REFRIGERACION | C36: 15000
B37: JOSE "CARAS" EQUIPO REFRIGERACION | C37: 5000
B38: LAR | I38: TENENCIA
B39: LORE (Transporte Personal) | I39: CONSEGUIR FACTURA
B40: MATERIAL RAISA | I40: FACTURAS | N40: NOTAS / PENDIENTES
B41: MK BOXES RUTH GDL | D41: 77738.85 | I41: MANTENIMIENTO DE INSTALACIONES | J41: 12800 | K41: 12800 | N41: Factura
B42: PATAGONIA CAJA CARTON y 30 lbs | C42: 31215.6 | I42: REPARACION DE SUSPENSIÓN DE CAMIONETA FORD | J42: 12800 | K42: 12800 | N42: Factura
B43: PATAGONIA CAJA CARTON y 30 lbs | C43: =9802 -> 9802 | I43: REPARACION DE MOTOR DE CAMIONETA | J43: 19450 | K43: 19450 | N43: Factura
B44: PATAGONIA CAJA CARTON y 30 lbs | C44: =16.9*1.16*700 -> 13722.8 | I44: MANTENIMIENTO DE ELECTRICO | J44: 17800 | K44: 17800 | N44: Factura
B45: PRIMUS LAB | C45: 6086.26 | I45: SERVICIO Y FRENOS CAMIONETA MAZDA | J45: 9850 | K45: 9850
B46: ROBERTO REYES | I46: SERVICIO Y FRENOS AUTOMOVIL AVEO | J46: 5500 | K46: 5500 | L46: =40000*1.16 -> 46400
B47: SAM JARABES TAPATIOS | J47: =SUM(J41:J46) -> 78200 | K47: =SUM(K41:K46) -> 78200 | N47: =J47*0.065 -> 5083 | O47: Honorarios
B48: SANICHEM
B49: SINDULFO | F49: 49247.8 | I49: OTROS GASTOS
B50: BATAS, DIESEL, HOMEDEPOT | I50: FACTURAS | J50: Cantidad | K50: Unidad | L50: P.Unitario | M50: Importe
B51: AVV MONARCA | C51: 11000 | I51: Caja de Carton de 30 lbs | J51: 4000 | K51: pzas | L51: =16.9*1.16 -> 19.604 | M51: =J51*L51 -> 78416 | N51: 231839.34
B52: IMPUESTOS LAR | C52: 13428 | I52: Caja de Carton de 20 lbs | J52: 4000 | K52: pzas | L52: =15.75*1.16 -> 18.27 | M52: =J52*L52 -> 73080
C53: =SUM(C7:C52) -> 314720.91 | D53: =SUM(D7:D52) -> 263589.84 | F53: =SUM(F7:F52) -> 110840.66 | I53: Caja de Carton de 10 lbs | J53: 7000 | K53: pzas | L53: =9.9*1.16 -> 11.484 | M53: =J53*L53 -> 80388
I54: Rollo emplaye de Plastico | J54: 40 | K54: pzas | L54: =130*1.16 -> 150.8 | M54: =J54*L54 -> 6032 | N54: 34546.99
I55: Tarima de Madera | J55: 100 | K55: pzas | L55: 285.15 | M55: =J55*L55 -> 28515
M57: =SUM(M51:M56) -> 266431 | N57: =SUM(N51:N56) -> 266386.33
I58: NOTAS / PENDIENTES | N58: =K47+N57 -> 344586.33
B59: NOTAS / PENDIENTES | J59: =J47 -> 78200
B60: Malla Sombra 70%, 7.85 x 4.70 mts | C60: 2 pzas | J60: =M57 -> 266431
B61: Malla Sombra 70%, 1.90 x 2.43 | C61: 2 pzas | I61: TOTAL FACTURAS YA NETO | J61: =SUM(J59:J60) -> 344631
B62: Malla Sombra 70%; 1.92 x 6.00 | C62: 2 pzas | D62: 1250
B63: P. Malla Sombra 70%; 1.25 x 2.50 mts | C63: 2 pzas | D63: 1250
B64: P. Malla Sombra 70%; 2.00 x 2.50 mts | C64: 1 pza | D64: 6250 | L64: CÁLCULOS
B65: P. Malla Sombra 70%; 2.50 x 2.50 mts | C65: 1 pza | L65: =M65/1.16 -> 297095.69 | M65: =J47+M57 -> 344631
L66: =L65*0.16 -> 47535.31
L67: =SUM(L65:L66) -> 344631 | M67: =M65*0.065 -> 22401.015
B70: JOSE HDEZ GARCIA (PAGO TARIMA)
B71: CIPSA (Control de Plagas)
